Workbook

Sheet Scopus
A1: Authors | B1: Author(s) ID | C1: Title | D1: Year | E1: Source title | F1: Volume | G1: Issue | H1: Art. No. | I1: Page start | J1: Page end | K1: Page count | L1: Cited by | M1: DOI | N1: Link | O1: Affiliations | P1: Authors with affiliations | Q1: Abstract | R1: Author Keywords | S1: Index Keywords | T1: Correspondence Address | U1: Editors | V1: Publisher | W1: ISSN | X1: ISBN | Y1: CODEN | Z1: PubMed ID | AA1: Language of Original Document | AB1: Abbreviated Source Title | AC1: Document Type | AD1: Publication Stage | AE1: Access Type | AF1: Source | AG1: EID
A2: Ren H.; Wallhagen M.; Bahrami A.; Cehlin M. | B2: 58508037500; 36706721900; 57197657593; 12786288600 | C2: Life Cycle Impacts of Timber and Reinforced Concrete Floor Slabs: A Comparative Assessment | D2: 2025 | E2: Infrastructures | F2: 10 | G2: 12 | H2: 346 | L2: 0 | M2: 10.3390/infrastructures10120346 | N2: https://www.scopus.com/pages/publications/105025941668?origin=resultslist | O2: Department of Building Engineering, Energy Systems and Sustainability Science, Faculty of Engineering and Sustainable Development, University of Gävle, Gävle, 801 76, Sweden | P2: Ren H., Department of Building Engineering, Energy Systems and Sustainability Science, Faculty of Engineering and Sustainable Development, University of Gävle, Gävle, 801 76, Sweden; Wallhagen M., Department of Building Engineering, Energy Systems and Sustainability Science, Faculty of Engineering and Sustainable Development, University of Gävle, Gävle, 801 76, Sweden; Bahrami A., Department of Building Engineering, Energy Systems and Sustainability Science, Faculty of Engineering and Sustainable Development, University of Gävle, Gävle, 801 76, Sweden; Cehlin M., Department of Building Engineering, Energy Systems and Sustainability Science, Faculty of Engineering and Sustainable Development, University of Gävle, Gävle, 801 76, Sweden | Q2: Due to their sustainability, lightweight qualities, and simplicity of installation, wood slab systems have gained increasing attention in the building industry. Cross-laminated timber (CLT), an engineered wood product (EWP), improves structural strength and stability, offering a good alternative to conventional reinforced concrete (RC) slab systems. Conventional CLT, however, contains adhesives that pose environmental and end-of-life (EOL) disposal challenges. Adhesive-free CLT (AFCLT) panels have recently been introduced as a sustainable option, but their environmental performance has not yet been thoroughly investigated. In this study, the environmental impacts of five slab systems are evaluated and compared using the life cycle assessment (LCA) methodology. The investigated slab systems include a standard CLT slab (SCLT), three different AFCLT slabs (AFCLT1, AFCLT2, and AFCLT3), and an RC slab. The assessment considered abiotic depletion potential (ADP), global warming potential (GWP), ozone layer depletion potential (ODP), human toxicity potential (HTP), freshwater aquatic ecotoxicity potential (FAETP), marine aquatic ecotoxicity potential (MAETP), terrestrial ecotoxicity potential (TETP), photochemical oxidation potential (POCP), acidification potential (AP), and eutrophication potential (EP), covering the entire life cycle from production to disposal, excluding part of the use stage (B2-B7). The results highlight the advantages and drawbacks of each slab system, providing insights into selecting sustainable slab solutions. AFCLT2 exhibited the lowest environmental impacts across the assessed categories. On the contrary, the RC slab showed the highest environmental impact among the studied products. For example, the RC slab had the highest GWP of 67.422 kg CO2 eq, which was 1784.3% higher than that of AFCLT2 (3.779 kg CO2 eq). Additionally, the simulation displayed that the analysis results vary depending on the electricity source, which is influenced by geographical location. Using the Norwegian electricity mix resulted in the most sustainable outcomes compared with Sweden, Finland, and Saudi Arabia. This study contributes to the advancement of low-carbon construction techniques and the development of building materials with reduced environmental impacts in the construction sector. © 2025 by the authors. | R2: adhesive-free; cross-laminated timber; life cycle assessment; slab; sustainability | T2: H. Ren; Department of Building Engineering, Energy Systems and Sustainability Science, Faculty of Engineering and Sustainable Development, University of Gävle, Gävle, 801 76, Sweden; email: ren.honghao@hig.se | V2: Multidisciplinary Digital Publishing Institute (MDPI) | W2: 24123811 | AA2: English | AB2: Infrastructures | AC2: Article | AD2: Final | AE2: All Open Access; Gold Open Access; Green Open Access | AF2: Scopus | AG2: 2-s2.0-105025941668
A3: Becker I.; Anderson F.; Phillips A.R. | B3: 58315871900; 58315621200; 56642281000 | C3: Structural design of hybrid steel-timber buildings for lower production stage embodied carbon emissions | D3: 2023 | E3: Journal of Building Engineering | F3: 76 | H3: 107053 | L3: 17 | M3: 10.1016/j.jobe.2023.107053 | N3: https://www.scopus.com/pages/publications/85161998408?origin=resultslist | O3: Department of Civil & Environmental Engineering, Washington State University, Pullman, 99163, WA, United States | P3: Becker I., Department of Civil & Environmental Engineering, Washington State University, Pullman, 99163, WA, United States; Anderson F., Department of Civil & Environmental Engineering, Washington State University, Pullman, 99163, WA, United States; Phillips A.R., Department of Civil & Environmental Engineering, Washington State University, Pullman, 99163, WA, United States | Q3: Using cross laminated timber (CLT) floor panels in combination with steel framing has been identified as a promising new structural configuration that can reduce the embodied greenhouse gas emissions of buildings. This project evaluated efficient structural design of hybrid steel-timber floor sections for a wide range of design parameters to determine the reductions in global warming potential possible relative to a conventional steel-concrete cross section. Each of the structural designs was checked for strength limit states, deflection, and minimum fire rating of either unrated, 1-h, or 2-h for a range of deck spans between 2.3 m and 4.6 m and beam spans between 5.5 m and 13.5 m. For an unrated floor assembly there is little global warming potential benefit to use steel-timber floors if a topping slab is included on top of the CLT slab. Whereas, using steel-timber configurations without a topping slab result in the largest global warming potential reductions. For the 1-h and 2-h ratings, even steel-timber configurations with a 64 mm thick topping slab had up to 20% reduction in global warming potential compared to the steel-concrete alternative. Additionally, several considerations that can drastically affect the global warming potential results were discussed. The results from this project demonstrate the best practices for structural design of hybrid steel-timber buildings to reduce global warming potential of the superstructure frame by between 5% and 35% relative to conventional steel and concrete construction. © 2023 Elsevier Ltd | S3: Architectural design; Carbon; Concretes; Floors; Gas emissions; Global warming; Greenhouse gases; Timber; % reductions; Conventional steel; Cross laminated; Embodied carbons; Global warming potential; Laminated timber; Production stage; Steel concrete; Timber buildings; Timber floors; Structural design | T3: A.R. Phillips; Department of Civil & Environmental Engineering, Washington State University, Pullman, 99163, United States; email: a.phillips@wsu.edu | V3: Elsevier Ltd | W3: 23527102 | AA3: English | AB3: J. Build. Eng. | AC3: Article | AD3: Final | AF3: Scopus | AG3: 2-s2.0-85161998408
A4: Salles E Portugal R.; Lawrence B.; Laleicke P.F.; Sinha A. | B4: 57203041069; 57203043062; 57201461333; 57203184231 | C4: Technical note: A preliminary study to quantify the environmental impacts of concrete and cork flooring | D4: 2018 | E4: Wood and Fiber Science | F4: 50 | G4: 1 | I4: 104 | J4: 112 | K4: =scopus[[#This Row],[Page end]]-scopus[[#This Row],[Page start]] -> 8 | L4: 8 | M4: 10.22382/wfs-2018-011 | N4: https://www.scopus.com/pages/publications/85050349907?origin=resultslist | O4: Department of Forest Biomaterials, North Carolina State University, Raleigh, 27695, NC, United States; Department of Wood Science and Engineering, Oregon State University, Corvallis, 97331, OR, United States | P4: Salles E Portugal R., Department of Forest Biomaterials, North Carolina State University, Raleigh, 27695, NC, United States; Lawrence B., Department of Forest Biomaterials, North Carolina State University, Raleigh, 27695, NC, United States; Laleicke P.F., Department of Forest Biomaterials, North Carolina State University, Raleigh, 27695, NC, United States; Sinha A., Department of Wood Science and Engineering, Oregon State University, Corvallis, 97331, OR, United States | Q4: Cross-laminated timber (CLT) is currently sought as a sustainable and green building material. It does not meet the International Building Code sound insulating requirements, and either a concrete slab or hardwood flooring is needed to meet the acoustic and vibrational performance benchmark. Cork, the bark of the cork oak, is well known for its sound insulating properties and often used for flooring applications in Europe. The cork-based flooring system is a potential solution to the acoustic problem faced by the CLT building industry. The goal of this preliminary study was to quantify the environmental impacts of a concrete and a cork-based flooring system that includes CLT. A life-cycle analysis (LCA) is conducted to focus on a cradle-to-gate comparison of a cork flooring system with a locally sourced concrete flooring system for use in a proposed CLT structure in Portland, OR. The LCA reveals that the global warming potential (GWP) of concrete is 25% higher for the concrete flooring system. For cork flooring, the GWP is mainly driven by inorganic compounds in the flooring assembly. The main source for cork is Portugal, which increases the GWP of the cork flooring system, in contrast to that of concrete flooring, which typically has a regional production and supply system. As environmental abatement costs increase, the profitability of cork flooring can increase to justify the creation of an appropriate system to close the loop. © 2018 by the Society of Wood Science and Technology. | R4: Cement; CLT; Cork; Flooring; LCA; Renewable; Sustainable | S4: Cork; Floors; Hardwoods; Inorganic Compounds; International; Life Cycle; Acoustic fields; Artificial life; Benchmarking; Building codes; Cements; Concrete construction; Concrete slabs; Construction industry; Environmental impact; Global warming; Hardwoods; Inorganic compounds; Life cycle; Sustainable development; Cork; Environmental abatement costs; Flooring; Global warming potential; Green building materials; International Building Code; Renewable; Sustainable; Floors | T4: P.F. Laleicke; Department of Forest Biomaterials, North Carolina State University, Raleigh, 27695, United States; email: Frederik@Laleicke.com | V4: Society of Wood Science and Technology | W4: 7356161 | Y4: WFSCD | AA4: English | AB4: Wood Fiber Sci | AC4: Article | AD4: Final | AE4: All Open Access; Gold Open Access | AF4: Scopus | AG4: 2-s2.0-85050349907
A5: Eslami H.; Yaghma A.; Jayasinghe L.B.; Waldmann D. | B5: 57272842800; 58604635500; 55626539700; 26636742700 | C5: INFLUENCE OF DIFFERENT END-OF-LIFE CYCLE SCENARIOS ON THE ENVIRONMENTAL IMPACTS OF TIMBER-CONCRETE COMPOSITE FLOOR SYSTEMS | D5: 2023 | E5: 13th World Conference on Timber Engineering, WCTE 2023 | F5: 2 | I5: 982 | J5: 988 | K5: =scopus[[#This Row],[Page end]]-scopus[[#This Row],[Page start]] -> 6 | L5: 10 | M5: 10.52202/069179-0134 | N5: https://www.scopus.com/pages/publications/85166200336?origin=resultslist | O5: FSTM University of Luxembourg, Luxembourg; Massivbau TU Darmstadt, Germany | P5: Eslami H., FSTM University of Luxembourg, Luxembourg; Yaghma A., FSTM University of Luxembourg, Luxembourg; Jayasinghe L.B., FSTM University of Luxembourg, Luxembourg; Waldmann D., Massivbau TU Darmstadt, Germany | Q5: Timber-concrete composite (TCC) floor systems attracted attention in the construction industry because of their low environmental impacts while demonstrating decent load-bearing capacity. However, the environmental impacts of possible end-of-life scenarios of TCC floors have not been extensively studied. To address this gap, a comprehensive life cycle assessment (LCA) study was conducted on three different slabs: a Reinforced concrete slab, a Steel concrete composite slab, and a CLT-concrete composite slab. The study revealed that the CLT-concrete composite slab has the lowest Global Warming Potential (GWP) among the three slabs. Subsequently, a more detailed LCA is performed on the CLT-concrete composite slab considering three different end-of-life scenarios of the CLT: 1. Energy recovery via incineration, 2. The prevailing scenario in Europe (a combination of energy recovery, recycling, and disposal), and 3. Reuse. The results show all three scenarios are beneficial in terms of GWP whereas the 3rd scenario is the most beneficial one. © (2023) WORLD CONFERENCE ON TIMBER ENGINEERING 2023 (WCTE 2023) All rights reserved. | R5: Environmental impact; Life cycle assessment; Reusable slab; Timber-concrete composite floor system | S5: Concrete slabs; Construction industry; Environmental impact; Floors; Forestry; Global warming; Reinforced concrete; Timber; Composite floor systems; Composite slab; Concrete composites; End of lives; Energy recovery; Global warming potential; Life cycle assessment; Reusable slab; Timber-concrete composite floor system; Timber-concrete composites; Life cycle | U5: Nyrud A.Q.; Malo K.A.; Nore K.; Alsen K.W.L.; Tulebekova S.; Staehr E.R.; Bergh G.; Wuyts W. | V5: World Conference on Timber Engineering (WCTE) | X5: 978-171387329-7 | AA5: English | AB5: World Conf. Timber Eng., WCTE | AC5: Conference paper | AD5: Final | AE5: All Open Access; Gold Open Access | AF5: Scopus | AG5: 2-s2.0-85166200336
A6: Hassan O.A.B.; Öberg F.; Gezelius E. | B6: 14022549700; 59429427900; 57210149692 | C6: Cross-laminated timber flooring and concrete slab flooring: A comparative study of structural design, economic and environmental consequences | D6: 2019 | E6: Journal of Building Engineering | F6: 26 | H6: 100881 | L6: 55 | M6: 10.1016/j.jobe.2019.100881 | N6: https://www.scopus.com/pages/publications/85069640267?origin=resultslist | O6: Department of Science and Technology, Linköping University, Norrköping, 601 74, Sweden; Drivhusvägen 38, Huskvarna, 56139, Sweden; Värmbolsvägen 3, Katrineholm, 641 51, Sweden | P6: Hassan O.A.B., Department of Science and Technology, Linköping University, Norrköping, 601 74, Sweden; Öberg F., Drivhusvägen 38, Huskvarna, 56139, Sweden; Gezelius E., Värmbolsvägen 3, Katrineholm, 641 51, Sweden | Q6: This paper compares cross-laminated timber (CLT) flooring and concrete slab flooring with respect to structural design, cost analysis, and greenhouse gas emissions. The effect of floor span on design values, costs, and carbon dioxide emissions is analysed in terms of structural design, economy, and environmental impact. Different cross-sections are chosen for this purpose. The study shows that CLT flooring has significantly lower emissions of climate-impact greenhouse gases, and its ability to store carbon is significantly greater than the capacity of concrete storage. From an economic point of view, the CLT material is more expensive than concrete. However, the estimated “ready-to-assemble” cost of both floor types is quite similar. The study shows that CLT flooring can compete with a concrete slab floor when it comes to a span as wide as 7 m without violating the structural requirements. However, with an increase in span, it is more difficult to meet the requirements for vibration for a CLT floor than for a concrete slab. At shorter spans, the moment capacity is often a decisive factor for concrete slabs while deformation is the decisive factor for a CLT floor. For larger spans, resonance frequency and deformation are crucial for the CLT floor, while the long-term deformation of the concrete is the decisive factor in structural design. © 2019 Elsevier Ltd | R6: Cost analysis; Eurocode 2; Eurocode 3; Greenhouse effects; Timber and concrete slabs | S6: Carbon dioxide; Codes (standards); Concrete slabs; Cost accounting; Cost benefit analysis; Deformation; Environmental impact; Finite difference method; Floors; Gas emissions; Global warming; Greenhouse effect; Greenhouse gases; Laminating; Structural design; Comparatives studies; Cost analysis; Cross laminated; Economic consequences; Environmental consequences; Eurocode 3; Eurocode2; Laminated timber; Timber and concrete slab; Timber floors; Timber | T6: O.A.B. Hassan; Department of Science and Technology, Linköping University, Norrköping, 601 74, Sweden; email: osama.hassan@liu.se | V6: Elsevier Ltd | W6: 23527102 | AA6: English | AB6: J. Build. Eng. | AC6: Review | AD6: Final | AF6: Scopus | AG6: 2-s2.0-85069640267
A7: Rauf A.; Shafiq M.T. | B7: 56592043300; 55671258600 | C7: Reducing Embodied Energy of Floor Assembly: A Case for Using CLT in Mid-Rise Residential Buildings | D7: 2024 | E7: Lecture Notes in Civil Engineering | F7: 389 | I7: 157 | J7: 163 | K7: =scopus[[#This Row],[Page end]]-scopus[[#This Row],[Page start]] -> 6 | L7: 2 | M7: 10.1007/978-981-99-6368-3_14 | N7: https://www.scopus.com/pages/publications/85185826337?origin=resultslist | O7: Department of Architectural Engineering, College of Engineering, United Arab Emirates University, Al Ain, Abu Dhabi, 15551, United Arab Emirates | P7: Rauf A., Department of Architectural Engineering, College of Engineering, United Arab Emirates University, Al Ain, Abu Dhabi, 15551, United Arab Emirates; Shafiq M.T., Department of Architectural Engineering, College of Engineering, United Arab Emirates University, Al Ain, Abu Dhabi, 15551, United Arab Emirates | Q7: Buildings’ energy consumption is estimated between 30 and 40% of its global use, resulting in various environmental impacts. There is a need to reduce the energy consumption by buildings in the construction phase, along with the operation phase, which is well-studied. Concrete is a construction material that is being used widely in the construction industry but has high embodied energy. In the move towards using low-energy materials, new materials and construction technologies are being developed and studied. In this regard, Cross lamented timber (CLT) can be a sustainable alternative due to its excellent load-carrying capabilities, and therefore has become an emerging choice in buildings as a low embodied energy material alternative. This paper aims to explore the potential initial embodied energy reduction benefits by comparing the initial embodied energy consumption of concrete floor systems and CLT floor systems for mid-rise residential buildings. An eight-story apartment building was used for this analysis. This study shows that replacing the reinforced concrete floor with a CLT floor results in more than four times reduction in embodied energy associated with floor construction. This demonstrates the need for careful selection of materials in buildings at the design stage to reduce their embodied energy and consider the use of CLT instead of reinforced concrete in this context. Results from this initial study also indicate the need for more studies to address the challenges associated with the adoption of this low embodied energy material. © The Author(s), under exclusive license to Springer Nature Singapore Pte Ltd. 2024. | R7: Construction materials; Cross-laminated timber; Floor assembly; Initial embodied energy; Input–output based hybrid assessment | S7: Apartment houses; Construction industry; Energy utilization; Environmental impact; Hybrid materials; Reinforced concrete; Timber; Cross laminated; Cross-laminated timber; Embodied energy; Energy materials; Floor assembly; Initial embodied energy; Input-output; Input–output based hybrid assessment; Laminated timber; Residential building; Floors | T7: A. Rauf; Department of Architectural Engineering, College of Engineering, United Arab Emirates University, Abu Dhabi, Al Ain, 15551, United Arab Emirates; email: a.rauf@uaeu.ac.ae | U7: Casini M. | V7: Springer Science and Business Media Deutschland GmbH | W7: 23662557 | X7: 978-981996367-6 | AA7: English | AB7: Lect. Notes Civ. Eng. | AC7: Conference paper | AD7: Final | AF7: Scopus | AG7: 2-s2.0-85185826337
A8: Chiniforush A.A.; Akbarnezhad A.; Valipour H.; Dackermann U. | B8: 57190258599; 36730725400; 6508258428; 29667491700 | C8: Dynamic response of steel-timber composite (STC) beams | D8: 2017 | E8: 24th International Congress on Sound and Vibration, ICSV 2017 | L8: 14 | N8: https://www.scopus.com/pages/publications/85029448417?origin=resultslist | O8: Centre for Infrastructure Engineering and Safety, School of Civil and Environmental Engineering, University of New South Wales, Sydney, NSW, Australia | P8: Chiniforush A.A., Centre for Infrastructure Engineering and Safety, School of Civil and Environmental Engineering, University of New South Wales, Sydney, NSW, Australia; Akbarnezhad A., Centre for Infrastructure Engineering and Safety, School of Civil and Environmental Engineering, University of New South Wales, Sydney, NSW, Australia; Valipour H., Centre for Infrastructure Engineering and Safety, School of Civil and Environmental Engineering, University of New South Wales, Sydney, NSW, Australia; Dackermann U., Centre for Infrastructure Engineering and Safety, School of Civil and Environmental Engineering, University of New South Wales, Sydney, NSW, Australia | Q8: Due to their recyclability and considerably lower embodied carbon, timber floors are advocated extensively as a more sustainable alternative to concrete slabs. Cross-Laminated Timber (CLT) is an engineered wood product with low variability in mechanical properties and therefore of high reliability and quality, presenting a very attractive alternative to concrete slabs. Replacing the reinforced concrete slabs in conventional steel-concrete composite with an engineered timber product (such as CLT) leads to a significant reduction in the overall weight of the floors, and consequently the weight of supporting structural elements including columns and beams. The combination of light CLT panels and steel may allow an increase in the load-carrying span of the floor systems which is highly desirable from an architectural viewpoint. However, one major drawback negatively affecting the serviceability and thus widespread adoption of such systems in practice is the high susceptibility of undesirable vibration in steel-timber composite (STC) floors under service load conditions due to low mass and damping ratio of timber slabs. This paper presents the results of a series of experimental impact hammer tests conducted to investigate the vibrational characteristics of different STC beams. Three STC beams with different shear connector types are experimentally tested to extract their natural frequencies. Numerical models are generated and validated using the results of previously performed short-term failure tests. The validated numerical models are then used to extract the linear flexural stiffness of STC beams to determine the deflection of the beams under self-weight. The experimental results are compared against results from analytical models calculating the fundamental natural frequencies of the beams. Further, the obtained dynamic indices of STC beams are evaluated based on available standard regulations. | R8: Cross laminated timber (CLT); Impact hammer testing; Steel-timber composite (STC) beams; Vibration serviceability of floors | S8: Building materials; Carbon; Composite structures; Concrete slabs; Concretes; Floors; Hammers; Laminated composites; Laminating; Natural frequencies; Numerical models; Reinforced concrete; Steel testing; Wood products; Architectural viewpoints; Cross laminated; Engineered wood products; Impact hammer testing; Impact hammer tests; Service load condition; Short-term failures; Vibration serviceability; Timber | U8: Gibbs B. | V8: International Institute of Acoustics and Vibration, IIAV | AA8: English | AB8: Int. Congr. Sound Vib., ICSV | AC8: Conference paper | AD8: Final | AF8: Scopus | AG8: 2-s2.0-85029448417
A9: Mirdad M.A.H.; Daneshvar H.; Joyce T.; Chui Y.H. | B9: 57190062072; 36730729900; 57204966326; 7004982369 | C9: Sustainability Design Considerations for Timber-Concrete Composite Floor Systems | D9: 2021 | E9: Advances in Civil Engineering | F9: 2021 | H9: 6688076 | L9: 21 | M9: 10.1155/2021/6688076 | N9: https://www.scopus.com/pages/publications/85103552039?origin=resultslist | O9: Department of Civil and Environmental Engineering, University of Alberta, 9211 116 Street NW, Edmonton, T6G1H9, AB, Canada | P9: Mirdad M.A.H., Department of Civil and Environmental Engineering, University of Alberta, 9211 116 Street NW, Edmonton, T6G1H9, AB, Canada; Daneshvar H., Department of Civil and Environmental Engineering, University of Alberta, 9211 116 Street NW, Edmonton, T6G1H9, AB, Canada; Joyce T., Department of Civil and Environmental Engineering, University of Alberta, 9211 116 Street NW, Edmonton, T6G1H9, AB, Canada; Chui Y.H., Department of Civil and Environmental Engineering, University of Alberta, 9211 116 Street NW, Edmonton, T6G1H9, AB, Canada | Q9: Over the last few decades, there has been growing interest in the use of low-carbon materials to reduce the environmental impacts of the construction industry. The advent of mass timber panels (MTP), such as cross laminated timber (CLT), has allowed structural engineers to specify a low-carbon material for a variety of floor design considerations. However, serviceability issues such as vibration and deflection are limiting the construction of longer span timber-only floor systems and have encouraged the development of timber-concrete composite (TCC) systems. The use of concrete would negatively impact on the carbon footprint of the TCC floor system and should be minimized. The purpose of this study was to study the impact on embodied carbon in the TCC system, when the ratio of timber and concrete was varied for specific floor spans. Two MTP products were considered, CLT and glued laminated timber (GLT). The floors were designed to satisfy structural, acoustic, and vibration criteria, and the results were presented in the form of span tables. It was found that using thicker MTP instead of adding concrete thickness to meet a specific span requirement can lead to lower embodied carbon values. Increasing concrete thickness for long-span floor systems led to a reduction in allowable floor span due to the vibration criterion being the controlling design parameter. Increasing timber thickness also resulted in higher strength and stiffness to weight ratios, which would contribute toward reducing the size of lateral load resisting systems and foundations, resulting in further reductions in the embodied carbon of the entire structure. © 2021 Md Abdul Hamid Mirdad et al. | T9: M.A.H. Mirdad; Department of Civil and Environmental Engineering, University of Alberta, Edmonton, 9211 116 Street NW, T6G1H9, Canada; email: mdabdul@ualberta.ca; M.A.H. Mirdad; Department of Civil and Environmental Engineering, University of Alberta, Edmonton, 9211 116 Street NW, T6G1H9, Canada; email: mdabdul@ualberta.ca | V9: Hindawi Limited | W9: 16878086 | AA9: English | AB9: Adv. Civ. Eng. | AC9: Article | AD9: Final | AE9: All Open Access; Gold Open Access; Green Open Access | AF9: Scopus | AG9: 2-s2.0-85103552039
A10: Ijeoma M.W.; Ou S.; Nabati A.; Chen H.; Stoner M.; Layton P.; Albright D.; Ross B.; Pang W.; Carbajales-Dale M. | B10: 58644049100; 58577750400; 36601248800; 58643831700; 57193124992; 6602579104; 57193121876; 16547000500; 24315073800; 56703480100 | C10: Environmental benefits of using an all-wood floor system in midrise office construction: an LCA based comparative case study in the Southeastern United States | D10: 2025 | E10: Environmental Research Communications | F10: 7 | G10: 11 | H10: 115024 | L10: 0 | M10: 10.1088/2515-7620/ae1f6a | N10: https://www.scopus.com/pages/publications/105034173755?origin=resultslist | O10: School of Civil and Environmental Engineering and Earth Sciences, Clemson University, United States; Wood Utilization + Design Institute, Clemson University, United States; School of Architecture, Clemson University, United States | P10: Ijeoma M.W., School of Civil and Environmental Engineering and Earth Sciences, Clemson University, United States; Ou S., School of Civil and Environmental Engineering and Earth Sciences, Clemson University, United States; Nabati A., School of Civil and Environmental Engineering and Earth Sciences, Clemson University, United States; Chen H., School of Civil and Environmental Engineering and Earth Sciences, Clemson University, United States; Stoner M., School of Civil and Environmental Engineering and Earth Sciences, Clemson University, United States; Layton P., Wood Utilization + Design Institute, Clemson University, United States; Albright D., School of Architecture, Clemson University, United States; Ross B., School of Civil and Environmental Engineering and Earth Sciences, Clemson University, United States; Pang W., School of Civil and Environmental Engineering and Earth Sciences, Clemson University, United States; Carbajales-Dale M., School of Civil and Environmental Engineering and Earth Sciences, Clemson University, United States | Q10: This study presents a cradle-to-grave whole-building life cycle assessment (WBLCA) of two functionally equivalent mid-rise commercial office buildings in Atlanta, Georgia: one constructed using mass timber with an all-wood composite floor system (CLT and GLT), and the other using conventional steel and reinforced concrete. Using Tally®, a Revit-integrated LCA tool, environmental impacts were evaluated across eight categories: global warming, acidification, eutrophication, smog formation, ozone depletion, total primary energy, renewable and non-renewable energy use, and normalized to 1 m2 of floor area over a 50-year service life. Results showed that the mass timber building required 25% less material mass and achieved a 4.5% reduction in global warming potential (GWP) (2801.12 kg CO2-eq/m2 versus 2975.85 kg CO2-eq/m2 for the steel–concrete system) and 27.9% more renewable energy use. However, timber’s carbon advantage was diminished by conservative end-of-life modeling, assuming 63.5% wood landfilling and 98% steel recycling, which significantly influenced net GWP through Module D credits. Additionally, the mass timber building stored 857,551 tCO2-eq in wood components (long-term biogenic carbon storage). The timber structure also exhibited higher eutrophication and acidification impacts, primarily due to emissions from adhesives and chemical treatments. Contribution analysis showed that finishes and non-structural components contributed disproportionately to overall impacts in both systems, illustrating the limitations of focusing solely on structural materials in building LCA. The findings emphasize the need for integrated material strategies, circular end-of-life planning, and regionally grounded modeling to fully realize the environmental potential of wood-based construction. © 2025 The Author(s). Published by IOP Publishing Ltd. | R10: biogenic carbon; cross laminated timber; mid-rise office buildings; U.S. Southeast; whole building life cycle assessment; wood composite floor system | S10: United States; building; carbon; comparative study; composite; construction; floor; life cycle analysis; timber; wood | T10: M.W. Ijeoma; School of Civil and Environmental Engineering and Earth Sciences, Clemson University, United States; email: mijeoma@clemson.edu | V10: Institute of Physics | W10: 25157620 | AA10: English | AB10: Environ. Res. Commun. | AC10: Article | AD10: Final | AE10: All Open Access; Gold Open Access; Green Open Access | AF10: Scopus | AG10: 2-s2.0-105034173755
A11: Cleghorn S.; Callaghan A. | B11: 59984081900; 58591306600 | C11: BALANCING FASTENER SPACING, ACOUSTICS, AND SPAN LENGTH IN EXPOSED CLT FLOOR-CEILING ASSEMBLIES | D11: 2025 | E11: Proceedings from the 14th World Conference on Timber Engineering: Advancing Timber for the Future Built Environment, WCTE 2025 | I11: 1416 | J11: 1422 | K11: =scopus[[#This Row],[Page end]]-scopus[[#This Row],[Page start]] -> 6 | L11: 0 | M11: 10.52202/080513-0173 | N11: https://www.scopus.com/pages/publications/105010279515?origin=resultslist | O11: Pliteq Inc., Toronto, Canada; Pliteq Inc., Vancouver, Canada | P11: Cleghorn S., Pliteq Inc., Toronto, Canada; Callaghan A., Pliteq Inc., Vancouver, Canada | Q11: Aside from sustainability, one of the most unique benefits of mass timber as a construction material is its extremely high strength-to-weight ratio. As a result, the weight of a floor slab in a mass timber building is much lighter than in a building constructed with conventional material. This unique benefit of engineered timber also comes with unique challenges. Albeit ironic, the low mass in mass timber assemblies is to blame for two of the most prominent pain points in engineered timber construction: floor vibration and sound transmission. Limits on floor vibration often result in short span lengths and tight structural grid spacing. Timber-concrete composite (TCC) floor systems are one method that can be used to alleviate this restriction. However, connecting a concrete topping to the timber panel underneath with mechanical fasteners harms the acoustic performance of the floor assembly. In this paper, the relationship between fastener spacing, composite slab behaviour, and sound transmission is investigated. Physical testing is carried out to determine the degree of composite action achieved with a timber-concrete composite system in the presence of a resilient acoustic interlayer. The data obtained is used to analyse the resulting span and acoustic performance with various spacing of fasteners. © (2025) WORLD CONFERENCE ON TIMBER ENGINEERING 2025 (WCTE 2025) All rights reserved. | R11: Acoustics; Cross Laminated Timber; Span; Vibration | S11: Acoustic wave transmission; Architectural acoustics; Concrete slabs; Fasteners; Structural dynamics; Timber; Transmissions; Wooden buildings; Wooden construction; Acoustic performance; Cross laminated; Cross laminated timber; Floor vibrations; Laminated timber; Sound transmission; Span; Span length; Timber-concrete composites; Vibration; Floors | U11: Rischmiller K.; Saleem M.A.; Downey C.; Gattas J.; Hossy D.; Ottenhaus L.; Wu W.; Zhang Y.; Yan Z. | V11: World Conference on Timber Engineering (WCTE) | X11: 979-833132089-8 | AA11: English | AB11: Proc. from World Conf. Timber Eng.: Adv. Timber Future Built Environ., WCTE | AC11: Conference paper | AD11: Final | AF11: Scopus | AG11: 2-s2.0-105010279515
A12: Park J.H.; Yuk H.; Kang S.T.; Kim S. | B12: 32867930500; 57219846158; 59722442600; 8542733000 | C12: Integrating thermal bridge analysis with life-cycle assessment: energy and environmental performance of Ply-Lam CLT envelopes in ZEB-Level apartments | D12: 2026 | E12: Building and Environment | F12: 290 | H12: 114169 | L12: 0 | M12: 10.1016/j.buildenv.2025.114169 | N12: https://www.scopus.com/pages/publications/105026165786?origin=resultslist | O12: Department of Architecture and Architectural Engineering, Yonsei University, Seoul, 03722, South Korea | P12: Park J.H., Department of Architecture and Architectural Engineering, Yonsei University, Seoul, 03722, South Korea; Yuk H., Department of Architecture and Architectural Engineering, Yonsei University, Seoul, 03722, South Korea; Kang S.T., Department of Architecture and Architectural Engineering, Yonsei University, Seoul, 03722, South Korea; Kim S., Department of Architecture and Architectural Engineering, Yonsei University, Seoul, 03722, South Korea | Q12: Building envelopes play a decisive role in both the operational energy use and life-cycle carbon emissions, particularly when junction thermal bridges are considered. In Korean apartment housing, reinforced concrete (RC) construction with interior insulation remains dominant; however, it is structurally vulnerable to heat losses at wall–slab connections. To address this drawback, ply-lam cross-laminated timber (CLT) was evaluated as an alternative envelope system using a coupled framework integrating ISO 10,211-based thermal bridge modeling, whole-building simulations in DesignBuilder, and life-cycle assessment (LCA), following EN 15,804+A2. Substituting RC walls with ply-lam CLT reduced annual primary energy consumption by 5%–9%. Junction thermal bridges in RC resulted in additional losses of 125.1 W/K, whereas the CLT alternative achieved only 13.0 W/K, representing an 89.6% reduction. Roof and corner junctions in CLT satisfied the stringent Ψ ≤ 0.05 W/m·K benchmark, whereas floor junctions approached this target. From a carbon perspective, CLT envelopes achieved an approximately 10% reduction in 30-year operational global warming potential (GWP) and further reductions in embodied GWP through lower manufacturing emissions and biogenic carbon storage, leading to a net decrease of approximately 59 kgCO₂eq/m² relative to RC. The results highlight the structural vulnerability of RC systems and the resilience of CLT alternatives when configured with continuous insulation and optimized details. By integrating junction-scale thermal bridge modeling with whole-building energy and life-cycle carbon analyses, this study provides comprehensive evidence for CLT as a competitive pathway to support low-carbon housing and national carbon neutrality goals. © 2025 | R12: Apartment; Cross-laminated timber; Life-cycle assessment; Thermal bridge; Zero-energy building | S12: Bridges; Carbon; Carbon cycle; Concrete slabs; Energy utilization; Intelligent buildings; Laminating; Life cycle; Life cycle assessment; Structural design; Walls (structural partitions); Zero energy buildings; % reductions; Apartment; Bridge analysis; Bridge model; Cross laminated; Cross-laminated timber; Global warming potential; Laminated timber; Thermal bridge; Zero energies; carbon emission; energy management; energy use; environmental assessment; life cycle analysis; Apartment houses | T12: S. Kim; Department of Architecture and Architectural Engineering, Yonsei University, Seoul, 03722, South Korea; email: kimsumin@yonsei.ac.kr | V12: Elsevier Ltd | W12: 3601323 | Y12: BUEND | AA12: English | AB12: Build. Environ. | AC12: Article | AD12: Final | AF12: Scopus | AG12: 2-s2.0-105026165786
A13: Sener K.; Mutlu E.; Anil O. | B13: 55366144500; 57215544445; 6508251680 | C13: A COMPARATIVE DESIGN AND LCA STUDY ON THE FEASIBILITY OF EARTHQUAKE-RESISTANT MASS-TIMBER BUILDINGS | D13: 2024 | E13: World Conference on Earthquake Engineering proceedings | F13: 2024 | L13: 0 | N13: https://www.scopus.com/pages/publications/105027857079?origin=resultslist | O13: Auburn University, Auburn, AL, United States; Gazi University, Ankara, Turkey | P13: Sener K., Auburn University, Auburn, AL, United States; Mutlu E., Auburn University, Auburn, AL, United States; Anil O., Gazi University, Ankara, Turkey | Q13: The building and construction industry drives the largest portion of global energy use and emissions. With climate change mitigation being a forefront topic of concern, the building and construction industry has a responsibility to alleviate its environmental impact, particularly in developing countries with a need for sustainable structural systems that explicitly consider environmental impact. Mass timber has recently emerged as a viable alternative to conventional construction materials and gained significant popularity in many developed nations. Recent design code advancements on mass timber elements and systems have paved the way for their use as multi-story building systems in seismic-prone regions. The devastating earthquakes that took place on February 3, 2023, in Turkiye have showcased the poor performance of the reinforced concrete building inventory. As the earthquakes affected a populated province where a vast majority of buildings sustained significant damage, hundreds of thousands of new buildings are expected to be constructed in the near term. Considering 93% of Turkiye’s population resides in considerably high earthquake-hazard regions, this rebuilding process gives a rare opportunity for constructing buildings with low-carbon structural solutions that utilize sustainable materials as well as modularity and prefabrication practices, therefore enabling the speedy constructability needed for the region. To evaluate the feasibility and potential benefits of seismic-resistant multi-story mass timber structures in Turkiye, this study conducts a comparative study between functionally equivalent reinforced concrete and mass timber buildings. The buildings use generic floor plans obtained from governmental agencies in Turkiye that mainly utilize shear wall systems for both gravity and lateral load resistance. The objective of the study was to investigate the design, lateral load performance, and economic aspects of the systems with a particular emphasis on sustainability through conducting a comparative life cycle assessment of mass timber relative to conventional reinforced concrete systems using realistic building layouts. The designed timber structure showcased adequate performance under seismic loads and was found to be considerably more environmentally advantageous compared to the companion reinforced concrete building. The mass-timber building resulted being more expensive based on material cost, but the difference is expected to shrink with more widespread CLT manufacturing in future. © 2024, International Association for Earthquake Engineering. All rights reserved. | S13: Concrete buildings; Concrete construction; Earthquake effects; Mortar; Seismic design; Structural dynamics; Wooden buildings; Building and construction; Climate change mitigation; Earthquake resistant; Energy emissions; Energy use; Global energy; Lateral loads; Reinforced concrete buildings; Timber buildings; Timber structures; Shear walls | V13: International Association for Earthquake Engineering | W13: 30065933 | AA13: English | AB13: World Conf. Earthq. Eng. Proc. | AC13: Book chapter | AD13: Final | AF13: Scopus | AG13: 2-s2.0-105027857079
A14: Lolli N.; Fufa S.M.; Kjendseth Wiik M. | B14: 56395455700; 49863337000; 57913703100 | C14: An assessment of greenhouse gas emissions from CLT and glulam in two residential nearly zero energy buildings | D14: 2019 | E14: Wood Material Science and Engineering | F14: 14 | G14: 5 | I14: 342 | J14: 354 | K14: =scopus[[#This Row],[Page end]]-scopus[[#This Row],[Page start]] -> 12 | L14: 33 | M14: 10.1080/17480272.2019.1655792 | N14: https://www.scopus.com/pages/publications/85070950776?origin=resultslist | O14: SINTEF, Building and Infrastructure, Trondheim, Norway; SINTEF, Building and Infrastructure, Oslo, Norway | P14: Lolli N., SINTEF, Building and Infrastructure, Trondheim, Norway; Fufa S.M., SINTEF, Building and Infrastructure, Oslo, Norway; Kjendseth Wiik M., SINTEF, Building and Infrastructure, Oslo, Norway | Q14: This paper analyses and compares the embodied and operational greenhouse gas (GHG) emissions of two nearly Zero Energy Buildings, a student housing building in Trondheim, Norway, and a residential building in Växjö, Sweden. The student housing in Trondheim, Moholt Allmenning Tower B, is a 9-storey tower composed of cross laminated timber (CLT) panels and concrete floor slabs with a total heated floor area of 3801 m2. The apartment building in Växjö, House A, consists of 8 floors composed of glued laminated timber (glulam) beams with a wood-cassette floor, and concrete slabs with a total heated floor area of 3483 m2. The results show that the use of CLT has the largest reduction of total GHG emissions due to substituting concrete elements in the structural frame. The comparative assessment of the external wall and the internal floor constructions shows that the use of CLT adds marginal GHG emissions per unit of area of component. The calculation of operational GHG emissions shows that the use of the Nordic electricity mix disfavours the full-electric energy system of Moholt Allmenning Tower B, in contrast to the district heating used in Norra Vallen Building A. © 2019, © 2019 Informa UK Limited, trading as Taylor & Francis Group. | R14: Cross laminated timber; environmental product declaration; glue laminated timber; greenhouse gas emission; life cycle assessment; nearly zero energy building | S14: Floors; Gluing; Greenhouse Gases; Heating; Lamination; Life Cycle; Apartment houses; Concrete slabs; Electric power systems; Floors; Gas emissions; Glues; Gluing; Greenhouse gases; Heating; Laminating; Life cycle; Timber; Wooden floors; Comparative assessment; Cross laminated; Electric energy systems; Environmental product declarations; Glue laminated timber; Glued laminated timber (glulam); Life Cycle Assessment (LCA); Residential building; Zero energy buildings | T14: N. Lolli; SINTEF, Building and Infrastructure, Trondheim, Norway; email: nicola.lolli@sintef.no | V14: Taylor and Francis Ltd. | W14: 17480272 | AA14: English | AB14: Wood Mater. Sci. Eng. | AC14: Article | AD14: Final | AF14: Scopus | AG14: 2-s2.0-85070950776
A15: Mirdad M.A.H.; Chui Y.H. | B15: 57190062072; 7004982369 | C15: Load-slip performance of Mass Timber Panel-Concrete (MTPC) composite connection with Self-tapping screws and insulation layer | D15: 2019 | E15: Construction and Building Materials | F15: 213 | I15: 696 | J15: 708 | K15: =scopus[[#This Row],[Page end]]-scopus[[#This Row],[Page start]] -> 12 | L15: 66 | M15: 10.1016/j.conbuildmat.2019.04.117 | N15: https://www.scopus.com/pages/publications/85064437748?origin=resultslist | O15: Department of Civil and Environmental Engineering, Donadeo Innovation Centre for Engineering, University of Alberta, Edmonton, T6G 1H9, Alberta, Canada | P15: Mirdad M.A.H., Department of Civil and Environmental Engineering, Donadeo Innovation Centre for Engineering, University of Alberta, Edmonton, T6G 1H9, Alberta, Canada; Chui Y.H., Department of Civil and Environmental Engineering, Donadeo Innovation Centre for Engineering, University of Alberta, Edmonton, T6G 1H9, Alberta, Canada | Q15: The Mass Timber Panel-Concrete (MTPC) composite floor systems are often encountered in mass timber buildings. Such a floor system consists of a Mass Timber Panel (MTP) connected to a reinforced concrete slab with Self-Tapping Screw (STS) connector and a sound insulation layer in between. In this study three types of MTPs with normal weight concrete, three insulation thicknesses, two screw embedment lengths and two screw angles were tested to characterize connection stiffness and strength. The main goal of this connection test program was to provide preliminary test data to assist in the development of an analytical model to predict connection lateral stiffness and strength considering the insulation layer in the MTPC system. Test results showed that connections with screws at an insertion angle of 30° had a larger stiffness and strength than connections with screws inserted at a 45° angle. Stiffness appears to be more sensitive to the presence of an insulation layer compared to strength. Overall, 35–50% and 55–65% reduction of serviceability stiffness, and 5–15% and 22–34% reduction of strength were noticed for an insulation thickness of 5 mm and 15 mm, respectively. Screws in Cross Laminated Timber (CLT) showed higher strength while screws in Glue Laminated Timber (GLT) showed higher stiffness, but the difference is insignificant in all three MTP products with different failure modes. © 2019 Elsevier Ltd | R15: Insulation layer; Mass timber panel; Self-tapping screw; Timber-concrete composite floor | S15: Concrete slabs; Floors; Laminating; Reinforced concrete; Screws; Software testing; Stiffness; Timber; Wooden buildings; Composite connections; Composite floor systems; Glue laminated timber; Insulation layers; Mass timber panel; Normal weight concrete; Self-tapping screws; Timber-concrete composites; Sound insulation | T15: M.A.H. Mirdad; Department of Civil and Environmental Engineering, Donadeo Innovation Centre for Engineering, University of Alberta, Edmonton, T6G 1H9, Canada; email: mdabdul@ualberta.ca | V15: Elsevier Ltd | W15: 9500618 | Y15: CBUME | AA15: English | AB15: Constr Build Mater | AC15: Article | AD15: Final | AF15: Scopus | AG15: 2-s2.0-85064437748
A16: Jafari M.; Sgambi L. | B16: 60173507600; 6506784463 | C16: Assessing the Environmental Performance of Hybrid Timber-Concrete Systems in High-Rise Building | D16: 2025 | E16: Proceedings of the International Conference of Architectural Science Association | I16: 166 | J16: 175 | K16: =scopus[[#This Row],[Page end]]-scopus[[#This Row],[Page start]] -> 9 | L16: 0 | M16: 10.65388/NUHN4734 | N16: https://www.scopus.com/pages/publications/105034748919?origin=resultslist | O16: Université Catholique de Louvain, Louvain-la-Neuve, Belgium | P16: Jafari M., Université Catholique de Louvain, Louvain-la-Neuve, Belgium; Sgambi L., Université Catholique de Louvain, Louvain-la-Neuve, Belgium | Q16: The construction industry has traditionally relied on reinforced concrete as the primary structural material in high-rise buildings, valued for its strength, durability, and fire resistance. However, its high environmental impact-mainly due to cement production, which contributes approximately 8% of global CO2 emissions-has raised concerns about its sustainability. As global efforts to reduce carbon emissions intensify, alternative construction approaches are gaining traction. Among them, hybrid timber-concrete systems offer a promising solution by combining the carbon-storing benefits of timber with the structural advantages of concrete. This study evaluates the environmental performance of hybrid timber-concrete systems in a 40-storey, 120-meter high-rise tower by comparing five structural typologies that vary in the number of Cross-Laminated Timber (CLT) floor slabs. The reference typology consists of a fully concrete frame with a cast-in-place concrete core, BubbleDeck slabs, and brick walls. The four alternative designs retain the concrete core while progressively replacing concrete slabs with CLT and using CLT for the walls. Structural modelling is conducted using Karamba 3D, while embodied greenhouse gas emissions (EGHGE) are quantified based on Global Warming Potential (GWP) indicators from the ÖKOBAUDAT database and EN 15804+A2 standards. Acoustic and fire performance are also evaluated, ensuring compliance with Belgian fire regulations and NBN EN ISO 16283 standards. The results show that total emissions decrease from 11.3 million to 7.45 million kgCO2e as CLT use increases-a reduction of over 34%. The study confirms the potential of hybrid systems to reduce embodied carbon while maintaining performance and regulatory compliance. © 2025, The Architectural Science Association and The University of Melbourne, Australia. | R16: embodied greenhouse gas emissions; high-rise buildings; Hybrid timber-concrete buildings; life cycle assessment | T16: M. Jafari; Université Catholique de Louvain, Louvain-la-Neuve, Belgium; email: Maryam.jafari@uclouvain.be | U16: Crawford R.H.; Stephan A.; Candido C.; Helal J.; Gobinath P. | V16: Architectural Science Association | W16: 22093850 | X16: 978-176373991-8 | AA16: English | AB16: Proc. Internat. Conf. Architech. Sci. Asso. | AC16: Conference paper | AD16: Final | AE16: All Open Access; Gold Open Access; Green Open Access | AF16: Scopus | AG16: 2-s2.0-105034748919
A17: Chapagain A.; Crovella P. | B17: 59961156800; 57190004292 | C17: Building Sustainable Futures: Evaluating Embodied Carbon Emissions and Biogenic Carbon Storage in a Cross-Laminated Timber Wall and Floor (Honeycomb) Mass Timber Building | D17: 2025 | E17: Sustainability (Switzerland) | F17: 17 | G17: 12 | H17: 5602 | L17: 4 | M17: 10.3390/su17125602 | N17: https://www.scopus.com/pages/publications/105008954389?origin=resultslist | O17: Department of Sustainable Resource Management, State University of New York College of Environmental Science and Forestry (SUNY ESF), 1 Forestry Drive, Syracuse, 13210, NY, United States | P17: Chapagain A., Department of Sustainable Resource Management, State University of New York College of Environmental Science and Forestry (SUNY ESF), 1 Forestry Drive, Syracuse, 13210, NY, United States; Crovella P., Department of Sustainable Resource Management, State University of New York College of Environmental Science and Forestry (SUNY ESF), 1 Forestry Drive, Syracuse, 13210, NY, United States | Q17: The building sector significantly contributes to global energy consumption and carbon emissions, primarily due to the extensive use of carbon-intensive materials such as concrete and steel. Mass timber construction, particularly using cross-laminated timber (CLT), offers a promising low-carbon alternative. This study aims to calculate the embodied carbon emissions and biogenic carbon storage of a CLT-based affordable housing project, 340+ Dixwell in New Haven, Connecticut. This project was designed using a honeycomb structural system, where mass timber floors and roofs are supported by mass timber-bearing walls. The authors are not aware of a prior study that has evaluated the life cycle impacts of honeycomb mass timber construction while considering Timber Use Intensity (TUI). Unlike traditional post-and-beam systems, the honeycomb design uses nearly twice the amount of timber, resulting in higher carbon sequestration. This makes the study significant from a sustainability perspective. This study follows International Standard Organization (ISO) standards 14044, 21930, and 21931 and reports the results for both lifecycle stages A1–A3 and A1–A5. The analysis covers key building components, including the substructure, superstructure, and enclosure, with timber, concrete, metals, glass, and insulation as the materials assessed. Material quantities were extracted using Autodesk Revit®, and the life cycle assessment (LCA) was evaluated using One Click LCA (2015)®. The A1 to A3 stage results of this honeycomb building revealed that, compared to conventional mass timber housing structures such as Adohi Hall and Heartwood, it demonstrates the lowest embodiedf carbon emissions and the highest biogenic carbon storage per square foot. This outcome is largely influenced by its higher Timber Use Intensity (TUI). Similarly, the A1-A5 findings indicate that the embodied carbon emissions of this honeycomb construction are 40% lower than the median value for other multi-family residential buildings, as assessed using the Carbon Leadership Forum (CLF) Embodied Carbon Emissions Benchmark Study of various buildings. Moreover, the biogenic carbon storage per square foot of this building is 60% higher than the average biogenic carbon storage of reference mass timber construction types. © 2025 by the authors. | R17: cross-laminated timber (CLT); honeycomb; life cycle assessment (LCA); Sustainable Construction; Timber Use Intensity (TUI) | S17: Connecticut; New Haven; United States; affordable housing; building construction; carbon emission; carbon storage; construction material; life cycle analysis; standard (regulation); timber | T17: P. Crovella; Department of Sustainable Resource Management, State University of New York College of Environmental Science and Forestry (SUNY ESF), Syracuse, 1 Forestry Drive, 13210, United States; email: plcrovella@esf.edu | V17: Multidisciplinary Digital Publishing Institute (MDPI) | W17: 20711050 | AA17: English | AB17: Sustainability | AC17: Article | AD17: Final | AE17: All Open Access; Gold Open Access | AF17: Scopus | AG17: 2-s2.0-105008954389
A18: Furukawa S.; Iwami R.; Kimura Y. | B18: 55737538800; 58771564400; 37088844100 | C18: Development of an Environmentally Friendly Steel Structural Framework: Evaluation of Bending Stiffness and Yield Bending Moment of Cross-Laminated Timber Slab–H-Shaped Steel Composite Beams for Component Reuse | D18: 2025 | E18: Sustainability (Switzerland) | F18: 17 | G18: 5 | H18: 2073 | L18: 5 | M18: 10.3390/su17052073 | N18: https://www.scopus.com/pages/publications/86000639763?origin=resultslist | O18: Graduate School of Engineering, Osaka Metropolitan University, Osaka, 558-8585, Japan; Graduate School of Engineering, Tohoku University, Sendai, 980-8579, Japan; KEN KEN Co., Ltd., Tokyo, 103-0012, Japan | P18: Furukawa S., Graduate School of Engineering, Osaka Metropolitan University, Osaka, 558-8585, Japan, Graduate School of Engineering, Tohoku University, Sendai, 980-8579, Japan; Iwami R., KEN KEN Co., Ltd., Tokyo, 103-0012, Japan; Kimura Y., Graduate School of Engineering, Tohoku University, Sendai, 980-8579, Japan | Q18: The building and construction sector accounts for nearly 40% of global greenhouse gas emissions, with steel-framed buildings being a significant contributor due to high CO2 emissions during production. To mitigate this issue, integrating Cross-Laminated Timber (CLT) into structural systems has emerged as a sustainable alternative. CLT, known for its carbon sequestration properties, offers an environmentally friendly replacement for reinforced-concrete slabs, particularly when paired with steel structures to enhance material reuse and reduce lifecycle impacts. This study focuses on hybrid systems combining H-shaped steel beams and CLT floor panels connected using high-strength friction bolts. A four-point bending test, simulating a secondary beam, was conducted, demonstrating that the composite effect significantly enhances flexural stiffness and strength. Additionally, a simplified method for evaluating the flexural stiffness and yielding strength of these composite beams, based on material and joint properties, was shown to successfully evaluate the test results. © 2025 by the authors. | R18: bolt friction joint; CLT floor panel; component reuse; steel structures | S18: bending; bolt; building; friction; greenhouse gas; reinforced concrete; replacement; steel structure; stiffness | T18: S. Furukawa; Graduate School of Engineering, Osaka Metropolitan University, Osaka, 558-8585, Japan; email: furukawa-s@omu.ac.jp | V18: Multidisciplinary Digital Publishing Institute (MDPI) | W18: 20711050 | AA18: English | AB18: Sustainability | AC18: Article | AD18: Final | AE18: All Open Access; Gold Open Access | AF18: Scopus | AG18: 2-s2.0-86000639763
A19: Morrell I.; Higgins C.; Sinha A.; Barbosa A.R. | B19: 57191162642; 57212721289; 57203184231; 55203435000 | C19: Experimental Assessment of Alternative Shear Connections in Cross-Laminated Timber-Concrete Floor Systems | D19: 2023 | E19: Journal of Structural Engineering (United States) | F19: 149 | G19: 5 | H19: 4023046 | L19: 6 | M19: 10.1061/JSENDH.STENG-11443 | N19: https://www.scopus.com/pages/publications/85149952497?origin=resultslist | O19: Dept. of Wood Science and Engineering, Oregon State Univ., Corvallis, 97331, OR, United States; School of Civil and Construction Engineering, Oregon State Univ., Corvallis, 97331, OR, United States | P19: Morrell I., Dept. of Wood Science and Engineering, Oregon State Univ., Corvallis, 97331, OR, United States; Higgins C., School of Civil and Construction Engineering, Oregon State Univ., Corvallis, 97331, OR, United States; Sinha A., Dept. of Wood Science and Engineering, Oregon State Univ., Corvallis, 97331, OR, United States; Barbosa A.R., School of Civil and Construction Engineering, Oregon State Univ., Corvallis, 97331, OR, United States | Q19: New building code changes enable mass timber panels (MTP), including cross-laminated timber (CLT), to be used in moderate and tall buildings as a floor system, usually with a concrete topping. A floor system of CLT composite with a reinforced concrete topping slab can provide increased stiffness and strength, making the system more advantageous. Present connection methods used to produce composite action within timber-concrete composites (TCC) have limitations when considering constructability or performance. This study presents experimental results from four (4) shear connectors for CLT-concrete composite floor systems, including three developed for this study. The connectors included self-tapping screws (STS) at 45-degrees, a modified lag screw with an integral plate washer that bears on the CLT surface at installation, a steel angle anchored only at the end of the span, and an inverted-T steel section with stem perforations. Different tests were performed on the different connectors including individual fastener tests, push-off group tests, and full-scale one-way bending tests. The push-off group tests showed that the proposed washer-screw exhibited higher stiffness and strength than a conventional STS. The full-scale one-way bending testing showed that the STS specimen exhibited the lowest strength of the alternatives. The inverted-T section exhibited the highest stiffness, while the other three connections had similar stiffness to the STS. © 2023 American Society of Civil Engineers. | R19: Mass timber; Shear connectors; Timber-concrete composite (TCC) floors | S19: Bending tests; Concrete slabs; Domestic appliances; Floors; Laminated composites; Laminating; Reinforced concrete; Screws; Stiffness; Tall buildings; Composite floors; Cross laminated; Floor systems; Laminated timber; Mass timber; Push offs; Self-tapping screws; Shear connector; Timber-concrete composite floor; Timber-concrete composites; Timber | T19: I. Morrell; Dept. of Wood Science and Engineering, Oregon State Univ., Corvallis, 97331, United States; email: ian.morrell@oregonstate.edu | V19: American Society of Civil Engineers (ASCE) | W19: 7339445 | Y19: JSEND | AA19: English | AB19: J. Struct. Eng. | AC19: Article | AD19: Final | AF19: Scopus | AG19: 2-s2.0-85149952497
A20: Abolghassem Tehrani M.; Froese T.M. | B20: 57208547556; 7004593611 | C20: A comparative life cycle assessment of tall buildings with alternative structural systems: Wood vs. Concrete | D20: 2017 | E20: 6th CSCE-CRC International Construction Specialty Conference 2017 - Held as Part of the Canadian Society for Civil Engineering Annual Conference and General Meeting 2017 | F20: 1 | I20: 19 | J20: 28 | K20: =scopus[[#This Row],[Page end]]-scopus[[#This Row],[Page start]] -> 9 | L20: 6 | N20: https://www.scopus.com/pages/publications/85047094911?origin=resultslist | O20: University of British Columbia, Canada | P20: Abolghassem Tehrani M., University of British Columbia, Canada; Froese T.M., University of British Columbia, Canada | Q20: Life cycle assessment (LCA) has been a useful decision-making tool in sustainable building design, construction and building material selection. LCA can be a valuable tool in early design stages of a project to allow designers to quantify and compare environmental impacts of different building materials as well as after the building is constructed to assess new building material technologies that can inform future projects. Arising from a study of the construction of the world's tallest mass-timber building in Vancouver, this paper makes a comparison between two different construction technologies, wood and concrete, to understand the environmental benefits and drawbacks of each technology in terms of 9 LCA impact categories. Two 18-storey residential buildings in Vancouver, Canada, were considered for this study, a traditional cast-in-place concrete frame building and a mass-timber hybrid design using glulam and CLT. The scope of this study was limited to the assessment of foundations, structures, floors, columns, beams, and roofs. Floor plans, elevation views and material quantities were obtained from construction drawings and were entered into LCA software (Athena's Impact Estimator) to obtain the two buildings' LCA results. These indicated that in 8 of the 9 impact categories, the wood building had lower environmental impacts and in 1 impact category (total primary energy) the concrete building had lower environmental impact. The variation of the results of this study with other LCA studies is considered to be due to different building types, location, system boundary, scope of the study, variation in wood construction techniques, and different LCA methodology. This study was conducted as part of a course project and acts as a placeholder study for a more detailed LCA in the future. © 2017 by Canadian Society for Civil Engineering. All rights reserved. | S20: Architectural design; Cast in place concrete; Decision making; Ecodesign; Environmental technology; Floors; Intelligent buildings; Life cycle; Sustainable development; Tall buildings; Timber; Wooden buildings; Wooden construction; Comparative life cycle assessment; Construction drawings; Construction technologies; Decision making tool; Environmental benefits; Life Cycle Assessment (LCA); New building materials; Sustainable building design; Environmental impact | T20: T.M. Froese; University of British Columbia, Canada; email: Thomas.Froese@ubc.ca | V20: Canadian Society for Civil Engineering | X20: 978-151087841-9 | AA20: English | AB20: CSCE-CRC Int. Constr. Spec. Conf. - Held Part Can. Soc. Civ. Eng. Annu. Conf. Gen. Meet. | AC20: Conference paper | AD20: Final | AF20: Scopus | AG20: 2-s2.0-85047094911
A21: Keipour N.; Valipour H.R.; Bradford M.A. | B21: 57193123892; 6508258428; 7102411221 | C21: Steel-timber versus Steel-Concrete Composite floors: A numerical study | D21: 2016 | E21: WCTE 2016 - World Conference on Timber Engineering | L21: 0 | N21: https://www.scopus.com/pages/publications/85010931951?origin=resultslist | O21: University of New South Wales, Australia | P21: Keipour N., University of New South Wales, Australia; Valipour H.R., University of New South Wales, Australia; Bradford M.A., University of New South Wales, Australia | Q21: Concrete is the most widely used construction material in the world. This material causes formation and release of CO2 and high energy consumption during manufacturing. One way to decrease concrete consumption negative consequences is to replace it with lower needed primary energy materials, like timber. The engineered wood products such as laminated veneer lumber (LVL) and cross laminated timber (CLT/X-lam) with improved structural characteristics, durability and fire resistance have made it possible for structural engineers to design and construct large multi-storey multi-bay buildings. Use of timber in structures is beneficial from both structural and environmental points of view. To name a few advantages, it has low carbon foot print, less energy consumption to be manufactured, less demand of work force, deconstruction capability, fast installation and low self-weight that ultimately lead to smaller size for structural component (e.g. beams and columns and foundation dimensions). In this paper, at first behaviour of Steel-Timber Composite (STC) simple 2bay beam with prefabricated cross banded LVL slabs with coach screws (self-tapping screws are assumed to be utilised for transferring the interface shear between the steel girder and the prefabricated timber slab and providing a composite connection) is captured by a nonlinear finite element model and the results are compared with similar Steel-Concrete Composite (SCC) system. Concrete hybrid structures have slightly higher strength and stiffness in compare to timber hybrid structures; On the other hand, timber structures are lighter, less pollutant and green to the environment, have simpler and faster and cheaper fabrication process and can be dismantled to recycling its structural components. Moreover, in a 1bay simple beam, effect of different parameters such as screw size, screw spacing, length of beam, timber slab and beam size on the load carrying capacity and composite efficiency of the STC system with LVL slab are evaluated. Results show that, screw spacing effect is more than screw size effect. In other words, in order to reach high strength and stiffness and appropriate composite action between slab and beam, also to avoid brittle failure, it is highly recommended to use many smaller diameters screws instead of few large diameters ones. | R21: FEM; LVL; Steel-concrete composite(SCC); Steel-timber composite(STC) | S21: Composites; Concrete; Steel; Beams and girders; Building materials; Carbon; Concretes; Energy utilization; Fasteners; Finite element method; Fire resistance; Laminating; Product design; Screws; Stiffness; Timber; Wood products; Engineered wood products; High energy consumption; Laminated veneer lumber; Non-linear finite element model; Steel-concrete composite; Steel-concrete composite floor; Strength and stiffness; Structural characteristics; Structural design | V21: Vienna University of Technology | X21: 978-390303900-1 | AA21: English | AB21: WCTE - World Conf. Timber Eng. | AC21: Conference paper | AD21: Final | AF21: Scopus | AG21: 2-s2.0-85010931951
A22: Rodrigues M.; Motal T.; Horváth Z. | B22: 57201152960; 58572372700; 57302536400 | C22: LABORATORY MEASUREMENTS OF LIGHTWEIGHT FLOATING FLOOR SYSTEMS ON CROSS-LAMINATED TIMBER (CLT) SLABS | D22: 2023 | E22: Proceedings of the International Congress on Sound and Vibration | L22: 1 | N22: https://www.scopus.com/pages/publications/85170649513?origin=resultslist | O22: CDM Stravitec, Brussels, Belgium; CDM Stravitec, Prague, Czech Republic; CDM Stravitec, Budapest, Hungary | P22: Rodrigues M., CDM Stravitec, Brussels, Belgium; Motal T., CDM Stravitec, Prague, Czech Republic; Horváth Z., CDM Stravitec, Budapest, Hungary | Q22: Mass timber solutions, including cross-laminated timber (CLT), are an excellent substitute to the more traditional fossil fuel-intensive construction materials. The use of these mass timber products allows for the reduction of the carbon footprint of the built environment. Nevertheless, the use of mass timber poses some rather unique challenges in terms of acoustics. Moreover, one of the most desired aspects of mass timber construction is the ability to leave a building's structure exposed as finish, which creates the need for asymmetric assemblies. Consequently, when talking about floor/ceiling applications, it is preferable that any acoustic component be installed on top of the assembly. One of the main advantages of mass timber is the strength-to-weight ratio, which allows for lighter setups than would be possible with other slab-type building materials. This reduces the overall mass of the building, which in turn offers many other benefits, such as reduced seismic forces and smaller building foundation requirements. To maintain these benefits and reduce the carbon footprint of the building, adding the mass of a concrete slab to improve the acoustic performance is not the best solution, leaving only the option of adding decouplers. To measure airborne sound reduction and impact noise isolation of lightweight floating floor systems and confirm that CLT-assemblies can provide satisfactory sound insulation, CDM Stravitec conducted a test campaign at the Belgian Building Research Institute. During this campaign, different types of decouplers were tested, including discrete bearings with various thicknesses and/or different void depths (filled entirely or partially with insulation material) and resilient mats and strips placed between the CLT slab and the different timber, cement and gypsum-based boards and this with and without the use of the well-known constrained layer damping technique. This paper presents the findings of that test campaign. © 2023 Proceedings of the International Congress on Sound and Vibration. All rights reserved. | R22: building acoustics; cross-laminated timber; floating floors; timber construction | S22: Carbon footprint; Concrete slabs; Fossil fuels; Laminating; Sound insulation; Wooden floors; Building acoustics; Cross laminated; Cross-laminated timber; Decouplers; Floating floor; Floating floor systems; Laboratory measurements; Laminated timber; Test campaign; Timber construction; Timber | U22: Carletti E. | V22: Society of Acoustics | W22: 23293675 | X22: 978-801103423-8 | AA22: English | AB22: Proc. Int. Congr. Sound Vib. | AC22: Conference paper | AD22: Final | AF22: Scopus | AG22: 2-s2.0-85170649513
A23: Qadourah J.A.; Al-Falahat A.M.; Alrwashdeh S.S. | B23: 57483250600; 57194287907; 57160166900 | C23: INVESTIGATE THE CARBON FOOTPRINTS OF THREE INTERMEDIATE FLOORING SYSTEMS: CROSS-LAMINATED TIMBER, SOLID CONCRETE, AND HOLLOW-CORE PRECAST CONCRETE | D23: 2022 | E23: Journal of Applied Engineering Science | F23: 20 | G23: 2 | I23: 377 | J23: 385 | K23: =scopus[[#This Row],[Page end]]-scopus[[#This Row],[Page start]] -> 8 | L23: 15 | M23: 10.5937/jaes0-32783 | N23: https://www.scopus.com/pages/publications/85128618069?origin=resultslist | O23: Department of Architecture and Building Technology, Faculty of Engineering, Mutah University, P.O. Box 7, Al-Karak, 61710, Jordan; Mechanical Engineering Department, Faculty of Engineering, Mutah University, P.O Box 7, Al-Karak, 61710, Jordan | P23: Qadourah J.A., Department of Architecture and Building Technology, Faculty of Engineering, Mutah University, P.O. Box 7, Al-Karak, 61710, Jordan; Al-Falahat A.M., Mechanical Engineering Department, Faculty of Engineering, Mutah University, P.O Box 7, Al-Karak, 61710, Jordan; Alrwashdeh S.S., Mechanical Engineering Department, Faculty of Engineering, Mutah University, P.O Box 7, Al-Karak, 61710, Jordan | Q23: This paper evaluates and compares the embodied energy and embodied carbon using a Life Cycle Assessment (LCA) approach for three different intermediate floor structures, all of which use prefabricated materials-cross-laminated timber (CLT), precast hollow-core concrete, and solid concrete-to decide which floor construction materials have less environmental impact for use in the construction of a semi-detached house in the UK. The Inventory of Carbon & Energy (ICE) and the Carbon Calculator tool were used to calculate the carbon footprint from “cradle to grave” to determine whether the use of a CLT solution provides improved environmental performance over the traditional concrete solutions. The carbon footprint results indicate that the use of a hollow-core precast concrete floor system emits less carbon than the other two systems, although the concrete requires more fossil fuel input than the timber during the manufacturing process, so based on this, the footprint from cradle to gate for the timber was expected to be the less than that of the concrete. However, the results show the opposite; this is because of the differences in the material quantities needed in each system. © 2022 Institut za Istrazivanja. All rights reserved. | R23: cradle-to-gate; cross-laminated timber; embodied energy; environmental impact; greenhouse gas emissions; life-cycle assessment; sustainable materials | T23: J.A. Qadourah; Department of Architecture and Building Technology, Faculty of Engineering, Mutah University, Al-Karak, P.O. Box 7, 61710, Jordan; email: Jenan.abuqadourah@mutah.edu.jo | V23: Institute for Educational Research | W23: 14514117 | AA23: English | AB23: J. Appl. Eng. Sci. | AC23: Article | AD23: Final | AE23: All Open Access; Gold Open Access; Green Open Access | AF23: Scopus | AG23: 2-s2.0-85128618069
A24: Alvarez D.; Kouda R.; Ho A.D.; Kubota T. | B24: 57225833403; 58482285300; 58414175100; 23025368600 | C24: Scenario analysis of embodied energy and CO2 emissions for multistory apartments in Indonesia | D24: 2023 | E24: E3S Web of Conferences | F24: 396 | H24: 4015 | L24: 1 | M24: 10.1051/e3sconf/202339604015 | N24: https://www.scopus.com/pages/publications/85164521513?origin=resultslist | O24: Graduate School of Advanced Science and Engineering, The University of Hiroshima, Hiroshima, Japan | P24: Alvarez D., Graduate School of Advanced Science and Engineering, The University of Hiroshima, Hiroshima, Japan; Kouda R., Graduate School of Advanced Science and Engineering, The University of Hiroshima, Hiroshima, Japan; Ho A.D., Graduate School of Advanced Science and Engineering, The University of Hiroshima, Hiroshima, Japan; Kubota T., Graduate School of Advanced Science and Engineering, The University of Hiroshima, Hiroshima, Japan | Q24: Contribution in the building sector to the global warming can be tackled by diminishing greenhouse gas (GHG) emissions (mainly CO2) not only from operational energy but also from the embodied energy (EE) of construction materials. Harvested Wood Products (HWP) such as Cross Laminated Timber (CLT), Glued Laminated (Glulam) timber, among others, make multistorey wooden buildings possible. These wooden buildings could help to reduce EE and CO2emissions significantly. A material flow analysis (MFA) using an I-O (Input-Output) table was used to compare three scenarios for an 8-story apartment building in Indonesia (total floor area: 9140 m2): First, the building had a reinforced concrete structure. Second, the building had a "hybrid"structure with reinforced concrete cores and first-floor elements, consisting of CLT floor panels, and Glulam columns and beams. Third, the building used only CLT panels besides reinforced concrete cores. The results showed that the last scenario achieved the largest CO2emissions and embodied energy reductions (58 t-CO2and 905 GJ), compared with the first scenario (81 t-CO2and 1110 GJ). Furthermore, we compare two methods to apply displacement factors (DF) to assess the CO2emissions savings for each CO2 ton in wood products substituted in place of non-wooden products between the three building scenarios. © The Authors, published by EDP Sciences, 2023. | R24: Displacement Factor; Embodied Energy; Material Sustainability; Wood harvested products | T24: D. Alvarez; Graduate School of Advanced Science and Engineering, The University of Hiroshima, Hiroshima, Japan; email: m220937@hiroshima-u.ac.jp | U24: Ooka R. | V24: EDP Sciences | W24: 25550403 | AA24: English | AB24: E3S Web Conf. | AC24: Conference paper | AD24: Final | AE24: All Open Access; Gold Open Access; Green Open Access | AF24: Scopus | AG24: 2-s2.0-85164521513
A25: Leonard S.; Parfitt K.; Solnosky R. | B25: 58266482800; 59198778400; 55843758900 | C25: Impact of Prescriptive Fire Design Provisions on Embodied Carbon for Mass Timber and Hybrid Mass Timber Floors | D25: 2024 | E25: Journal of Architectural Engineering | F25: 30 | G25: 3 | H25: 4024021 | L25: 0 | M25: 10.1061/JAEIED.AEENG-1695 | N25: https://www.scopus.com/pages/publications/85197284249?origin=resultslist | O25: Dept. of Architectural Engineering, Pennsylvania State Univ., 104 Engineering Unit A, University Park, 16802, PA, United States | P25: Leonard S., Dept. of Architectural Engineering, Pennsylvania State Univ., 104 Engineering Unit A, University Park, 16802, PA, United States; Parfitt K., Dept. of Architectural Engineering, Pennsylvania State Univ., 104 Engineering Unit A, University Park, 16802, PA, United States; Solnosky R., Dept. of Architectural Engineering, Pennsylvania State Univ., 104 Engineering Unit A, University Park, 16802, PA, United States | Q25: Structural mass timber has been used more often in buildings over the last 5 years, given its potential to be a sustainable alternative. However, concerns still exist around the fire safety of mass timber structures, and current mass timber building designers must consider a variety of fire protection strategies, including but not limited to noncombustible protection and design for sacrificial char thickness. This research focuses on better understanding how prescriptive code fire protection strategies affect the sustainability goals that have partially driven mass timber use. This paper studies how decisions during early design can reduce embodied carbon (EC), the initial energy use of a structure's construction. Five structural floor system types were modeled parametrically for various levels of fire protection. System types included timber-concrete composites, cross-laminated timber (CLT)-steel hybrids, and all-timber systems. The resulting EC data analysis reveals that all-timber systems perform the best for EC when the fully protected option is used at shorter spans, when the combined approach option is used at midrange spans, and when the fully exposed timber option is used at longer spans. Across all studied systems, the shallowest possible depth occurred for the 10-ft (3.05-m) spanning CLT-steel hybrid systems at 11.5 in. (292 mm) deep for the fully protected system, and the lowest possible EC was 10.5 lb CO2 eq/ft2 (51.3 kg CO2 eq/m2) for the fully protected 10-ft (3.05 m) all-timber system. © 2024 American Society of Civil Engineers. | R25: Cross-laminated timber (CLT); Embodied carbon; Glulam; Hybrid mass timber; Mass timber; Parametric model; Prescriptive fire design | S25: Carbon; Carbon dioxide; Fire extinguishers; Fire protection; Fires; Floors; Hybrid systems; Laminated composites; Laminating; Optimal systems; Structural design; Cross laminated; Cross-laminated timber; Embodied carbons; Fire designs; Glulam; Hybrid mass timber; Laminated timber; Mass timber; Parametric models; Prescriptive fire design; Timber | T25: S. Leonard; Dept. of Architectural Engineering, Pennsylvania State Univ., University Park, 104 Engineering Unit A, 16802, United States; email: sleonard@rdh.com | V25: American Society of Civil Engineers (ASCE) | W25: 10760431 | Y25: JAEIE | AA25: English | AB25: J Archit Eng | AC25: Article | AD25: Final | AF25: Scopus | AG25: 2-s2.0-85197284249
A26: Ahmed D.; Ayadat T.; Asiz A. | B26: 57217208973; 20435579500; 6506926796 | C26: Design and performance of high-rise structure using ultra-lightweight cross laminated timber floor system | D26: 2020 | E26: Proceedings of International Structural Engineering and Construction | F26: 7 | G26: 2 | I26: 1 | J26: 29 | K26: =scopus[[#This Row],[Page end]]-scopus[[#This Row],[Page start]] -> 28 | L26: 3 | M26: 10.14455/ISEC.2020.7(2).STR-29 | N26: https://www.scopus.com/pages/publications/85108433134?origin=resultslist | O26: Dept of Civil Engineering, Prince Mohammad Bin Fahd University, Al Khobar, Saudi Arabia | P26: Ahmed D., Dept of Civil Engineering, Prince Mohammad Bin Fahd University, Al Khobar, Saudi Arabia; Ayadat T., Dept of Civil Engineering, Prince Mohammad Bin Fahd University, Al Khobar, Saudi Arabia; Asiz A., Dept of Civil Engineering, Prince Mohammad Bin Fahd University, Al Khobar, Saudi Arabia | Q26: The main objective of this paper is to study the structural performance of a high-rise structure when alternative lightweight material known as cross-laminated timber was used as a slab in floor system in lieu of conventional reinforced concrete slab. A numerical case study was conducted using a highly irregular RC frame building with its two 60-story towers joined at the top. Three major analyses were considered. First, modeling and analyzing the building with an RC slab was conducted to determine the design reference. Second, substituting the RC slab with the CLT slab was performed using the same building skeleton. Third, redesigning and optimizing the building skeleton with that CLT to observe skeleton material saving obtained using the same structural performance criteria. Major lateral loads applicable in the Eastern Province of Saudi Arabia were inputted. Strengths and serviceability requirements for floor diaphragm and lateral load resisting system were checked first before performing a comparative analysis between traditional RC and CLT slabs as floor diaphragm. The structural performance criteria to be used for comparative study between RC and CLT slabs included total drift, inter-story drift due to lateral loads, and base reactions. Structural periods and acceleration responses for each floor were investigated and contrasted with the existing building code. The foundation demand was also investigated based on the structural weight and reactions generated from the RC and CLT floor systems. © 2020 ISEC Press. | R26: Floor diaphragm; Lateral deflections; Lateral loads; Tall buildings | U26: Askarinejad H.; Yazdani S.; Singh A. | V26: ISEC Press | W26: 2644108X | AA26: English | AB26: Proceedings of International Structural Engineering and Construction | AC26: Conference paper | AD26: Final | AF26: Scopus | AG26: 2-s2.0-85108433134
A27: Robertson A.B.; Lam F.C.F.; Cole R.J. | B27: 57213188922; 7102075782; 7401590488 | C27: A comparative cradle-to-gate life cycle assessment of mid-rise office building construction alternatives: Laminated timber or reinforced concrete | D27: 2012 | E27: Buildings | F27: 2 | G27: 3 | I27: 245 | J27: 270 | K27: =scopus[[#This Row],[Page end]]-scopus[[#This Row],[Page start]] -> 25 | L27: 209 | M27: 10.3390/buildings2030245 | N27: https://www.scopus.com/pages/publications/84887921198?origin=resultslist | O27: Canadian Wood Council, 400-99 Bank Street, Ottawa, K1P 6B9, ON, Canada; Department of Wood Science, Faculty of Forestry, University of British Columbia, 2424 Main Mall, Vancouver, V6T 1Z4, BC, Canada; School of Architecture and Landscape Architecture, University of British Columbia, 6333 Memorial Road, Vancouver, V6T 1Z2, BC, Canada | P27: Robertson A.B., Canadian Wood Council, 400-99 Bank Street, Ottawa, K1P 6B9, ON, Canada; Lam F.C.F., Department of Wood Science, Faculty of Forestry, University of British Columbia, 2424 Main Mall, Vancouver, V6T 1Z4, BC, Canada; Cole R.J., School of Architecture and Landscape Architecture, University of British Columbia, 6333 Memorial Road, Vancouver, V6T 1Z2, BC, Canada | Q27: The objective of this project was to quantify and compare the environmental impacts associated with alternative designs for a typical North American mid-rise office building. Two scenarios were considered; a traditional cast-in-place, reinforced concrete frame and a laminated timber hybrid design, which utilized engineered wood products (cross-laminated timber (CLT) and glulam). The boundary of the quantitative analysis was cradle-to-construction site gate and encompassed the structural support system and the building enclosure. Floor plans, elevations, material quantities, and structural loads associated with a five-storey concrete-framed building design were obtained from issued-for-construction drawings. A functionally equivalent, laminated timber hybrid design was conceived, based on Canadian Building Code requirements. Design values for locally produced CLT panels were established from in-house material testing. Primary data collected from a pilot-scale manufacturing facility was used to develop the life cycle inventory for CLT, whereas secondary sources were referenced for other construction materials. The TRACI characterization methodology was employed to translate inventory flows into impact indicators. The results indicated that the laminated timber building design offered a lower environmental impact in 10 of 11 assessment categories. The cradle-to-gate process energy was found to be nearly identical in both design scenarios (3.5 GJ/m2), whereas the cumulative embodied energy (feedstock plus process) of construction materials was estimated to be 8.2 and4.6 GJ/m2 for the timber and concrete designs, respectively; which indicated an increased availability of readily accessible potential energy stored within the building materials of the timber alternative. © 2012 by the authors. | R27: Cradle-to-gate; Cross-laminated timber; Embodied energy; Glulam; Material selection; Mid-rise office building; Reinforced concrete; Whole building life cycle assessment; Wood products | T27: A.B. Robertson; Canadian Wood Council, Ottawa, 400-99 Bank Street, K1P 6B9, Canada; email: adam.robertson@alumni.ubc.ca | V27: MDPI AG | W27: 20755309 | AA27: English | AB27: Buildings | AC27: Article | AD27: Final | AE27: All Open Access; Gold Open Access; Green Open Access | AF27: Scopus | AG27: 2-s2.0-84887921198
A28: Vilotijević J.; Premrov M. | B28: 59527242600; 6701482772 | C28: Assessment of In-Plane Timber Floor Stiffness as Structural Diaphragms: A Numerical Approach to Lateral Load Response | D28: 2025 | E28: Forests | F28: 16 | G28: 1 | H28: 56 | L28: 0 | M28: 10.3390/f16010056 | N28: https://www.scopus.com/pages/publications/85216030423?origin=resultslist | O28: Faculty of Civil Engineering, Transportation Engineering and Architecture, University of Maribor, Smetanova 17, Maribor, 2000, Slovenia | P28: Vilotijević J., Faculty of Civil Engineering, Transportation Engineering and Architecture, University of Maribor, Smetanova 17, Maribor, 2000, Slovenia; Premrov M., Faculty of Civil Engineering, Transportation Engineering and Architecture, University of Maribor, Smetanova 17, Maribor, 2000, Slovenia | Q28: The behaviour of horizontal floor diaphragms plays a crucial role in ensuring the overall response of a building during earthquakes, as the stiffness of these diaphragms determines whether the structure will act as an integrated system. If the diaphragms do not exhibit sufficient stiffness, differences in the redistribution of forces on wall elements arise, increasing the risk of significant deformations and even local damage, which is commonly observed in earthquake-affected areas. Additionally, flexible diaphragms heighten the risk of torsional effects. Due to these factors, more attention should be given to the response of buildings with flexible diaphragms. Eurocode standard specifies general requirements under which diaphragms should be considered rigid within their plane, depending on the maximum diaphragm moment. However, specific guidelines regarding the geometric and material properties of elements that significantly impact seismic behaviour are not included in the existing European standards. This served as a basis for conducting a numerical study analysing the in-plane behaviour of floor elements made from different materials. This study, limited to a simple box-shaped structure with masonry walls, symmetrical in both orthogonal directions, evaluated and thoroughly analysed the deformations for different types of diaphragms, including prefabricated wooden frame-panel floors, CLT panels, and reinforced concrete slabs. Special emphasis was placed on wooden structural elements due to the increased demand for timber construction, as the behaviour of these elements needs to be properly studied, especially in seismic regions. The study results were obtained through FEM analysis using the SCIA Engineer software, version 22. The modelling of elements was carried out considering the orthotropy of brick wall and wooden ceiling elements, as well as simulating the appropriate shear stiffness of the connecting means. © 2024 by the authors. | R28: concrete slab; cross-laminated timber; floor flexibility; horizontal diaphragms; lateral load resisting system; seismic design; timber frame-panel floor | S28: Diaphragms; Elements; Mortar; Reinforced Concrete; Specifications; Stiffness; Structural Analysis; Walls; Brick construction; Earthquake effects; Mortar; Reinforced concrete; Seismic design; Structural analysis; Structural dynamics; Structural panels; Timber; Walls (structural partitions); Wooden buildings; Wooden floors; Cross laminated; Cross-laminated timber; Flexible diaphragms; Floor flexibility; Horizontal diaphragms; Laminated timber; Lateral load resisting systems; Timber floors; Timber frame-panel floor; Timber frames; concrete structure; loading test; seismic design; seismic response; structural response; Concrete slabs | T28: M. Premrov; Faculty of Civil Engineering, Transportation Engineering and Architecture, University of Maribor, Maribor, Smetanova 17, 2000, Slovenia; email: miroslav.premrov@um.si | V28: Multidisciplinary Digital Publishing Institute (MDPI) | W28: 19994907 | AA28: English | AB28: Forests | AC28: Article | AD28: Final | AE28: All Open Access; Gold Open Access; Green Open Access | AF28: Scopus | AG28: 2-s2.0-85216030423
A29: Iwase T.; Sasaki T.; Araki S.; Huzita T.; Kayo C. | B29: 57216780552; 7407394908; 55510147800; 57204962702; 36986959800 | C29: Environmental and economic evaluation of small-scale bridge repair using cross-laminated timber floor slabs | D29: 2020 | E29: Sustainability (Switzerland) | F29: 12 | G29: 8 | H29: 3424 | L29: 12 | M29: 10.3390/SU12083424 | N29: https://www.scopus.com/pages/publications/85084653775?origin=resultslist | O29: Graduate School of Agriculture, Tokyo University of Agriculture and Technology, 3-5-8 Saiwai-cho, Fuchu, Tokyo, 183-8509, Japan; Research Faculty of Agriculture, Hokkaido University, Kita 9, Nishi, 9, Kita-ku, Sapporo, Hokkaido, 060-8589, Japan; Hattori Engineer Co., Ltd., 2-2-12 Miroku, Aoi-ku, Shizuoka, Shizuoka, 420-0053, Japan; United Graduate School of Agricultural Science, Tokyo University of Agriculture and Technology, 3-5-8 Saiwai-cho, Fuchu, Tokyo, 183-8509, Japan; Institute of Agriculture, Tokyo University of Agriculture and Technology, 3-5-8 Saiwai-cho, Fuchu, Tokyo, 183-8509, Japan | P29: Iwase T., Graduate School of Agriculture, Tokyo University of Agriculture and Technology, 3-5-8 Saiwai-cho, Fuchu, Tokyo, 183-8509, Japan; Sasaki T., Research Faculty of Agriculture, Hokkaido University, Kita 9, Nishi, 9, Kita-ku, Sapporo, Hokkaido, 060-8589, Japan; Araki S., Hattori Engineer Co., Ltd., 2-2-12 Miroku, Aoi-ku, Shizuoka, Shizuoka, 420-0053, Japan; Huzita T., United Graduate School of Agricultural Science, Tokyo University of Agriculture and Technology, 3-5-8 Saiwai-cho, Fuchu, Tokyo, 183-8509, Japan; Kayo C., Institute of Agriculture, Tokyo University of Agriculture and Technology, 3-5-8 Saiwai-cho, Fuchu, Tokyo, 183-8509, Japan | Q29: Cross-laminated timber (CLT) has gained popularity worldwide in recent years, and its use in buildings and civil engineering structures has attracted attention in Japan. In this study, the life-cycle greenhouse gas (GHG) balance and costs associated with CLT floor slabs were evaluated with respect to small-scale bridge repair as the first instance of the use of CLT in civil engineering projects in Japan. Additionally, waterproofing treatment was applied to CLT slabs, and the potential GHG and cost reduction of CLT in comparison with reinforced concrete (RC) slabs were examined. GHG emissions were the smallest for non-waterproofed CLT slabs and the greatest for RC slabs. When replacing RC slabs with CLT slabs without waterproofing, fossil-derived GHG emissions can be reduced by 73 kg-CO2eq/m2 per slab, and fossil/wood-derived GHG emissions can be reduced by 67 kg-CO2eq/m2; however, the use of disposed CLT as fuel is essential. Moreover, a reduction in GHG emissions can be expected if RC slabs are replaced with CLT slabs that are waterproofed only once every 20 years. Further, the cost associated with RC slabs is 20% of that attributable to CLT slabs. Hence, measures need to be taken to reduce the cost of CLT and waterproofing materials. © 2020 by the authors. | R29: Cross-laminated timber; Floor slabs; Greenhouse gas emissions; Life-cycle assessment; Reinforced concrete; Waterproofing treatment | S29: Japan; building; carbon emission; civil engineering; comparative study; delamination; environmental economics; greenhouse gas; reinforced concrete; repair; timber | T29: C. Kayo; Institute of Agriculture, Tokyo University of Agriculture and Technology, Fuchu, Tokyo, 3-5-8 Saiwai-cho, 183-8509, Japan; email: kayoc@cc.tuat.ac.jp | V29: MDPI | W29: 20711050 | AA29: English | AB29: Sustainability | AC29: Article | AD29: Final | AE29: All Open Access; Gold Open Access; Green Open Access | AF29: Scopus | AG29: 2-s2.0-85084653775
A30: Guo C.; Zhou J.; Chui Y.H. | B30: 57856104800; 57202383380; 7004982369 | C30: Experimental and numerical investigations on vibration performance of mass timber slab floors with floating concrete toppings | D30: 2025 | E30: Engineering Structures | F30: 330 | H30: 119919 | L30: 6 | M30: 10.1016/j.engstruct.2025.119919 | N30: https://www.scopus.com/pages/publications/85218124256?origin=resultslist | O30: School of Engineering, University of Northern British Columbia, Prince George, V2N 4Z9, BC, Canada; Department of Civil and Environmental Engineering, University of Alberta, Edmonton, T6G 1H9, AB, Canada | P30: Guo C., School of Engineering, University of Northern British Columbia, Prince George, V2N 4Z9, BC, Canada, Department of Civil and Environmental Engineering, University of Alberta, Edmonton, T6G 1H9, AB, Canada; Zhou J., School of Engineering, University of Northern British Columbia, Prince George, V2N 4Z9, BC, Canada; Chui Y.H., Department of Civil and Environmental Engineering, University of Alberta, Edmonton, T6G 1H9, AB, Canada | Q30: Mass timber floor systems face serviceability challenges such as deflection, sound insulation, and vibration due to their relatively light weight and low bending stiffness. Floating concrete topping is often applied to improve acoustic performance and fire resistance, though its impact on vibration performance is less understood. The current Canadian design standard CSA O86-24 suggests ignoring the effect of concrete topping when applying the vibration-controlled span equation if its area density is less than twice of the bare cross laminated timber (CLT) floor area density. Floating concrete toppings typically don't necessitate mechanical fasteners, although limited tests have shown partial composite behavior. This study experimentally investigated the vibration performance and dynamic properties of mass timber slab floors with floating concrete toppings, examining two dowel laminated timber (DLT) floors with varying thicknesses, spans, concrete topping thicknesses, floor assemblies, and boundary conditions. Effective bending stiffness was derived from experimental data as inputs for fundamental natural frequency calculation. Additionally, two finite element models were developed for modal analysis of mass timber floors with floating concrete toppings. Results demonstrated that the floating concrete topping could significantly enhance the floor system's vibration performance, improving an unacceptable bare timber floor to acceptable levels. However, its impact on the fundamental natural frequency depends in the thickness of the concrete topping and details of floating floor assemblies. Composite action between the concrete topping and timber slab existed even without mechanical fasteners, though the degree of this action varied across different assemblies. Accurate modeling of such floor systems can be achieved with careful consideration of input of material properties and partial composite action factors. © 2025 The Authors | R30: Dynamic properties; Floating concrete toppings; Mass timber floor systems; Numerical modelling; Vibration performance | S30: Concrete slabs; Convergence of numerical methods; Hydroelasticity; Laminated composites; Timber; Vibration analysis; Wooden floors; Area density; Dynamics properties; Floating concrete topping; Floor systems; Laminated timber; Mass timber floor system; Mechanical fastener; Performance; Timber floors; Vibration performance; concrete structure; dynamic analysis; dynamic property; experimental study; floor; numerical model; performance assessment; timber; vibration; Sound insulation | T30: J. Zhou; School of Engineering, University of Northern British Columbia, Prince George, V2N 4Z9, Canada; email: jianhui.zhou@unbc.ca | V30: Elsevier Ltd | W30: 1410296 | Y30: ENSTD | AA30: English | AB30: Eng. Struct. | AC30: Article | AD30: Final | AE30: All Open Access; Hybrid Gold Open Access | AF30: Scopus | AG30: 2-s2.0-85218124256
A31: Asiz A.; Smith I. | B31: 6506926796; 7404426235 | C31: Tall hybrid RC framed buildings with massive timber floor plates | D31: 2010 | E31: Structures and Architecture - Proceedings of the 1st International Conference on Structures and Architecture, ICSA 2010 | I31: 1377 | J31: 1384 | K31: =scopus[[#This Row],[Page end]]-scopus[[#This Row],[Page start]] -> 7 | L31: 2 | N31: https://www.scopus.com/pages/publications/84856657256?origin=resultslist | O31: University of New Brunswick, Canada | P31: Asiz A., University of New Brunswick, Canada; Smith I., University of New Brunswick, Canada | Q31: This paper discusses feasibility of using massive but lightweight Cross Laminated Timber (CLT) plates as floor and roof components of tall buildings constructed with reinforced concrete (RC) as the main skeleton. A case study using a 24-storey building designed with CLT floors is presented here along with a matched design of a building having traditional RC floors. Result indicate that structural benefits from substituting lightweight timber slabs for the traditional relatively heavy slabs are significant yielding potentially large savings in both the main structural skeleton and foundation systems. For example, lateral drift during a design level earthquake is predicted to be reduced by about 15 to 20 percent using mechanically equivalent CLT floor slabs in lieu of RC slabs typical of 'normal' construction. © 2010 Taylor & Francis Group, London. | S31: Architecture; Floors; Musculoskeletal system; Reinforced concrete; Tall buildings; Timber; Design levels; Floor slabs; Foundation systems; Laminated timber; Lateral drifts; RC slab; Structural skeletons; Timber floors; Plates (structural components) | X31: 978-041549249-2 | AA31: English | AB31: Struct. Archit. - Proc. Int. Conf. Struct. Archit., ICSA | AC31: Conference paper | AD31: Final | AF31: Scopus | AG31: 2-s2.0-84856657256
C32: 1st International Conference on Civil and Environmental Engineering for Resilient, Smart and Sustainable Solutions, 2024 | D32: 2025 | E32: Materials Research Proceedings | F32: 48 | L32: 0 | N32: https://www.scopus.com/pages/publications/105003211169?origin=resultslist | Q32: The proceedings contain 133 papers. The special focus in this conference is on Civil and Environmental Engineering for Resilient, Smart and Sustainable Solutions. The topics include: Evaluation of concrete slab exposed to weather conditions resulting from global warming; Shear capacity prediction of squat flanged walls using machine learning approach with CatBoost and CTGAN; Comprehensive analysis of structural beams: Theoretical calculations and simulation analysis using ANSYS; a modified design for improving pressure relief valve stability; site amplification using 1D seismic site response analysis in Islamabad: An application of building code of Pakistan 2021; critical building components analysis: An empirical study; Experimental study of BFRP-RC beams exposed to elevated temperatures; An optimization approach process of a 4-story RC building structural plan through generative design; Structural design analysis of hybrid multi-rise buildings, with CLT and LGS light weight floor system, at Neom-The Line; Sustainability and cost of a multi-story edifice, with CLT and LGS light weight floor system, at Neom-The Line; Seismic assessment of reinforced concrete building strengthened with CFRP sheets using non-linear static approach; cyclic performance of partially grouted reinforced masonry shear walls with boundary elements; a study case: Seismic evaluation of existing six-story office building with flat plate structural system; experimental evaluation of the masonry infilled reinforced concrete frame under reverse cyclic loading; comparative analysis of structural performance and cost efficiency of reinforced concrete and steel for a three-story warehouse in high-risk seismic zones; fire behaviour of mass timber beam-to-column hybrid connections-A state-of-the-art review; seismic assessment of masonry infilled frame structures. | U32: Ayadat T. | V32: Association of American Publishers | W32: 24743941 | X32: 978-164490341-4 | AA32: English | AB32: Mater. Res. Proc. | AC32: Conference review | AD32: Final | AF32: Scopus | AG32: 2-s2.0-105003211169
A33: Shahnewaz M.; Jackson R.; Tannert T. | B33: 55634928200; 57193120662; 22939744900 | C33: The Arbour: An Innovative Composite Floor System | D33: 2022 | E33: Structures Congress 2022 - Selected Papers from the Structures Congress 2022 | I33: 251 | J33: 259 | K33: =scopus[[#This Row],[Page end]]-scopus[[#This Row],[Page start]] -> 8 | L33: 2 | M33: 10.1061/9780784484180.022 | N33: https://www.scopus.com/pages/publications/85129179215?origin=resultslist | O33: Fast + Epp, Vancouver, Canada; UNBC, Prince George, Canada | P33: Shahnewaz M., Fast + Epp, Vancouver, Canada; Jackson R., Fast + Epp, Vancouver, Canada; Tannert T., UNBC, Prince George, Canada | Q33: The $130M Arbour, a 10-storey, 16,000 m2, exposed tall wood structure located on George Brown College's waterfront campus in Toronto, Canada, will serve as an educational hub for the college, housing the Tall Wood Research Institute, a childcare center, and teaching and social spaces. The innovative large-span beamless structural floor system is comprised of cross-laminated timber (CLT) concrete composite slab bands with perpendicular CLT infill panels, all supported on glulam columns. This long-span flat plate system allows for flexibility in architectural programming and unobstructed mechanical distribution; its performance was validated by full-scale laboratory tests. The project, currently under construction, received external funding through the National Resources Canada Green Constriction Wood Program, alongside other partners, to facilitate mass timber innovation specific to this project. This catalyzed a full-scale structural testing regime at the University of Northern British Columbia, investigating timber concrete composite "slab bands,"to determine their performance and develop a low-cost composite connector. © ASCE. | S33: Concrete slabs; Concrete testing; Laminated composites; Timber; Wooden buildings; Composite floor systems; Cross laminated; Laminated timber; Performance; Research institutes; Social spaces; Timber-concrete composite slabs; Toronto; Wood research; Wood structure; Floors | U33: Soules J.G. | V33: American Society of Civil Engineers (ASCE) | X33: 978-078448418-0 | AA33: English | AB33: Struct. Congr. - Sel. Pap. Struct. Congr. | AC33: Conference paper | AD33: Final | AF33: Scopus | AG33: 2-s2.0-85129179215
A34: Dachin C.; Niu Y. | B34: 59984771300; 59984546000 | C34: INNOVATIVE CONNECTION SOLUTIONS FOR TCC FLOOR SYSTEMS: MECHANICAL AND ENVIRONMENTAL ASSESSMENT | D34: 2025 | E34: Proceedings from the 14th World Conference on Timber Engineering: Advancing Timber for the Future Built Environment, WCTE 2025 | I34: 5444 | J34: 5451 | K34: =scopus[[#This Row],[Page end]]-scopus[[#This Row],[Page start]] -> 7 | L34: 0 | M34: 10.52202/080513-0670 | N34: https://www.scopus.com/pages/publications/105010259319?origin=resultslist | O34: HAMK Tech research unit, Häme University of Applied Sciences, Finland | P34: Dachin C., HAMK Tech research unit, Häme University of Applied Sciences, Finland; Niu Y., HAMK Tech research unit, Häme University of Applied Sciences, Finland | Q34: The need to reduce carbon emissions in the construction sector has highlighted timber as a viable substitute for carbon-intensive materials such as concrete. Cross-laminated timber (CLT), as a load-bearing element, has gained popularity in recent years due to its favorable structural characteristics and environmental benefits. The use of CLT in timber-concrete-composite (TCC) floor systems has been increasingly explored, but current building codes and standards have not been adapted accordingly. This limits design options, simultaneously fostering opportunities for innovation. In this paper, a new type of shear connector, designed to transfer forces between prefabricated CLT and concrete components in a TCC floor system, is experimentally investigated. The connector is part of a dry-dry system, in which both concrete and timber elements are prefabricated and assembled without wet processes, allowing rapid installation and potential disassembly. To evaluate environmental performance, a functionally equivalent hollow core slab (HCS) is designated as a reference for comparison. The relevant assessment is conducted using the life cycle assessment (LCA), where the manufacturing and end-of-life (EoL) stages are considered. The results reveal promising mechanical performance of the new connection solution for TCC, potential carbon benefits, and viable deconstructability and reusability. © (2025) WORLD CONFERENCE ON TIMBER ENGINEERING 2025 (WCTE 2025) All rights reserved. | R34: carbon emissions; CLT; dry-dry system; TCC; timber | S34: Artificial life; Carbon; Carbon emissions; Concretes; Construction industry; Ecodesign; Environmental impact assessments; Environmental management; Floors; Life cycle; Life cycle assessment; Reusability; 'Dry' [; Carbon emissions; Composite floor systems; Cross laminated; Cross-laminated timber; Dry-dry system; Laminated timber; Mechanical; Timber-concrete composites; Timber | U34: Rischmiller K.; Saleem M.A.; Downey C.; Gattas J.; Hossy D.; Ottenhaus L.; Wu W.; Zhang Y.; Yan Z. | V34: World Conference on Timber Engineering (WCTE) | X34: 979-833132089-8 | AA34: English | AB34: Proc. from World Conf. Timber Eng.: Adv. Timber Future Built Environ., WCTE | AC34: Conference paper | AD34: Final | AF34: Scopus | AG34: 2-s2.0-105010259319
A35: Skullestad J.L.; Bohne R.A.; Lohne J. | B35: 57192432255; 17433243900; 55794391200 | C35: High-rise Timber Buildings as a Climate Change Mitigation Measure - A Comparative LCA of Structural System Alternatives | D35: 2016 | E35: Energy Procedia | F35: 96 | I35: 112 | J35: 123 | K35: =scopus[[#This Row],[Page end]]-scopus[[#This Row],[Page start]] -> 11 | L35: 193 | M35: 10.1016/j.egypro.2016.09.112 | N35: https://www.scopus.com/pages/publications/85006456765?origin=resultslist | O35: Industrial Ecology Programme, Norwegian University of Science and Technology (NTNU), Høgskoleringen 1, Trondheim, 7491, Norway; Department of Civil and Transport Engineering, NTNU, Høgskoleringen 7A, Trondheim, 491, Norway; ASPLAN VIAK AS, Postboks 24, Sandvika, 1300, Norway | P35: Skullestad J.L., Industrial Ecology Programme, Norwegian University of Science and Technology (NTNU), Høgskoleringen 1, Trondheim, 7491, Norway, ASPLAN VIAK AS, Postboks 24, Sandvika, 1300, Norway; Bohne R.A., Department of Civil and Transport Engineering, NTNU, Høgskoleringen 7A, Trondheim, 491, Norway; Lohne J., Department of Civil and Transport Engineering, NTNU, Høgskoleringen 7A, Trondheim, 491, Norway | Q35: This paper reports on a study examining the potential of reducing greenhouse gas (GHG) emissions from the building sector by substituting multi-storey steel and concrete building structures with timber structures. Life cycle assessment (LCA) is applied to compare the climate change impact (CC) of a reinforced concrete (RC) benchmark structure to the CC of an alternative timber structure for four buildings ranging from 3 to 21 storeys. The timber structures are dimensioned to meet the same load criteria as the benchmark structures. The LCA comprises three calculation approaches differing in analysis perspective, allocation methods, and modelling of biogenic CO2 and carbonation of concrete. Irrespective of the assumptions made, the timber structures cause lower CC than the RC structures. By applying attributional LCA, the timber structures are found to cause a CC that is 34-84% lower than the RC structures. The large span is due to different building heights and methodological assumptions. The CC saving per m2 floor area obtained by substituting a RC structure with a timber structure decrease slightly with building height up to 12 storeys, but increase from 12 to 21 storeys. From a consequential LCA perspective, constructing timber structures can result in avoided GHG emissions, indicated by a negative CC. Compared to the RC structures, this equal savings greater than 100%. © 2016 The Authors. | R35: climate change mitigation; CLT; High-rise buildings; LCA; timber buildings | S35: Buildings; Carbon dioxide; Concretes; Gas emissions; Greenhouse gases; Life cycle; Reinforced concrete; Tall buildings; Timber; Wooden buildings; Benchmark structure; Calculation approaches; Climate change impact; Climate change mitigation; Concrete building structures; High rise building; Life Cycle Assessment (LCA); Timber buildings; Climate change | T35: J.L. Skullestad; Industrial Ecology Programme, Norwegian University of Science and Technology (NTNU), Trondheim, Høgskoleringen 1, 7491, Norway; email: juliel.skullestad@asplanviak.no | U35: Kurnitskin J. | V35: Elsevier Ltd | W35: 18766102 | AA35: English | AB35: Energy Procedia | AC35: Conference paper | AD35: Final | AE35: All Open Access; Gold Open Access; Green Open Access | AF35: Scopus | AG35: 2-s2.0-85006456765
A36: Barclay S.; Salem O.S. | B36: 58622584200; 53980457500 | C36: FIRE RESISTANCE TESTING OF CLT-CONCRETE COMPOSITE FLOOR SLABS UTILIZING SELF-TAPPING SCREWS AS SHEAR CONNECTORS | D36: 2023 | E36: 13th World Conference on Timber Engineering, WCTE 2023 | F36: 3 | I36: 1821 | J36: 1830 | K36: =scopus[[#This Row],[Page end]]-scopus[[#This Row],[Page start]] -> 9 | L36: 0 | N36: https://www.scopus.com/pages/publications/85172708777?origin=resultslist | O36: Dept. of Civil Engineering, Lakehead University, ON, Canada | P36: Barclay S., Dept. of Civil Engineering, Lakehead University, ON, Canada; Salem O.S., Dept. of Civil Engineering, Lakehead University, ON, Canada | Q36: In massive production, mass timber sections made of engineered wood, such as cross-laminated timber (CLT) panels, accelerated the pace of the construction of tall wood buildings in North America in the past few years. However, more stringent fire safety measures are applicable to tall timber buildings. Most critically, floor systems in mass timber buildings can be made more robust, span longer distances and exhibit enhanced fire resistance by adding a top layer of concrete to allow a timber-concrete composite (TCC) floor system when adequate shear connections are utilized. This paper presents the experimental results of the fire resistance tests of two full-size, one-way TCC floor slabs that utilized self-tapping screws (STS) as shear connectors. The main objective of this new experimental study is to investigate the enhancement of the fire performance when designing a CLT panel as a TCC floor assembly through achieving the required composite action with a top concrete layer at the interface between the two materials. Test results show that a minimum fire resistance of two hours required by applicable building codes for mid-rise residential buildings has been achieved for CLT floor panel by designing it as a TCC floor assembly, taking advantage of the composite action activated by the utilization of 45-degree inclined STS as shear connectors. © (2023) WORLD CONFERENCE ON TIMBER ENGINEERING 2023 (WCTE 2023) All rights reserved. | R36: Fire resistance; Self-tapping screws; Shear connectors; Timber-concrete composite sections | S36: Building codes; Concrete slabs; Timber; Wooden buildings; Wooden construction; Wooden floors; Composite floor slabs; Composite floors; Composite sections; Cross laminated; Laminated timber; Self-tapping screws; Shear connector; Timber buildings; Timber-concrete composite section; Timber-concrete composites; Fire resistance | U36: Nyrud A.Q.; Malo K.A.; Nore K.; Alsen K.W.L.; Tulebekova S.; Staehr E.R.; Bergh G.; Wuyts W. | V36: World Conference on Timber Engineering (WCTE) | X36: 978-171387329-7 | AA36: English | AB36: World Conf. Timber Eng., WCTE | AC36: Conference paper | AD36: Final | AF36: Scopus | AG36: 2-s2.0-85172708777
A37: Siddika A.; Mamun M.A.A.; Aslani F.; Zhuge Y.; Alyousef R.; Hajimohammadi A. | B37: 57194742493; 57202906536; 35788787900; 59680306200; 56554240700; 25927917700 | C37: Cross-laminated timber–concrete composite structural floor system: A state-of-the-art review | D37: 2021 | E37: Engineering Failure Analysis | F37: 130 | H37: 105766 | L37: 54 | M37: 10.1016/j.engfailanal.2021.105766 | N37: https://www.scopus.com/pages/publications/85116015307?origin=resultslist | O37: School of Civil and Environmental Engineering, University of New South Wales, Sydney, 2052, NSW, Australia; Department of Civil Engineering, Pabna University of Science and Technology, Pabna, 6600, Bangladesh; Department of Civil Engineering, Rajshahi University of Engineering and Technology, Rajshahi, 6204, Bangladesh; Materials and Structures Innovation Group, School of Engineering, University of Western Australia, 6009, WA, Australia; School of Engineering, Edith Cowan University, Joondalup, 6027, WA, Australia; School of Natural and Built Environments, University of South Australia, Adelaide, 5001, Australia; Department of Civil Engineering, College of Engineering, Prince Sattam Bin Abdulaziz University, Alkharj, 11942, Saudi Arabia | P37: Siddika A., School of Civil and Environmental Engineering, University of New South Wales, Sydney, 2052, NSW, Australia, Department of Civil Engineering, Pabna University of Science and Technology, Pabna, 6600, Bangladesh; Mamun M.A.A., Department of Civil Engineering, Rajshahi University of Engineering and Technology, Rajshahi, 6204, Bangladesh; Aslani F., Materials and Structures Innovation Group, School of Engineering, University of Western Australia, 6009, WA, Australia, School of Engineering, Edith Cowan University, Joondalup, 6027, WA, Australia; Zhuge Y., School of Natural and Built Environments, University of South Australia, Adelaide, 5001, Australia; Alyousef R., Department of Civil Engineering, College of Engineering, Prince Sattam Bin Abdulaziz University, Alkharj, 11942, Saudi Arabia; Hajimohammadi A., School of Civil and Environmental Engineering, University of New South Wales, Sydney, 2052, NSW, Australia | Q37: Composite construction elements are gaining extensive attention due to their high performance and reliability. Timber–concrete composite is one of the well-known engineered products of global interest. The cross-laminated timber (CLT) is a plate-like quasi-rigid composite that is usually composed of an uneven number of layers of solid timber board. The timber boards are generally placed side-by-side and arranged crosswise in CLT. The anisotropy in single timber boards is reliably adjusted, and its out-of-plane load bearing capacity is improved. The CLT members show low bending strength and resistance to global stability. The CLT–concrete composite has developed and showed approximately 3–5 times higher strength capacity than the conventional timber or concrete structures. This study aims to review the current practice and available guidelines for the CLT–concrete floor system. The basic required information on the design and construction and performance of the aforementioned system is described based on the current practices. This review can guide prospective researchers and users regarding the application of the CLT–concrete composite. The CLT–concrete elements need to be designed and constructed following the current code of practice and studies guidelines to achieve optimal performance. The design, construction, and performance of the CLT-concrete system are dependent on timber properties, connection systems, and slab details. This composite floor system possesses good performance under various loading conditions if adequately designed and constructed. © 2021 Elsevier Ltd | R37: cross-laminated timber (CLT); Fire performance; Seismic; Sustainability; Timber-concrete composite | S37: Bending strength; Concrete slabs; Floors; Laminated composites; Laminating; Optimal systems; Cross laminated; Cross-laminated timber; Current practices; Fire performance; Floor systems; Laminated timber; Performance; Timber boards; Timber-concrete; Timber-concrete composites; Timber | T37: A. Siddika; School of Civil and Environmental Engineering, University of New South Wales, Sydney, 2052, Australia; email: a.siddika@unsw.edu.au | V37: Elsevier Ltd | W37: 13506307 | Y37: EFANE | AA37: English | AB37: Eng. Fail. Anal. | AC37: Review | AD37: Final | AE37: All Open Access; Green Open Access | AF37: Scopus | AG37: 2-s2.0-85116015307
A38: Hatachi K.; Nishimiya W.; Mori T.; Araki Y.; Sakashita M.; Nakashima S.; Isoda H. | B38: 59983398100; 59984727200; 22958266500; 37114331300; 14064014300; 59983839500; 55350625300 | C38: CREEP BEHAVIOR OF CROSS-LAMINATED TIMBER-CONCRETE COMPOSITE FLOOR SYSTEM ON FIXED END CONDITION | D38: 2025 | E38: Proceedings from the 14th World Conference on Timber Engineering: Advancing Timber for the Future Built Environment, WCTE 2025 | I38: 3557 | J38: 3565 | K38: =scopus[[#This Row],[Page end]]-scopus[[#This Row],[Page start]] -> 8 | L38: 0 | M38: 10.52202/080513-0436 | N38: https://www.scopus.com/pages/publications/105010273928?origin=resultslist | O38: Graduate School of Advanced Science and Engineering, Hiroshima University, Hiroshima, Japan; Hiroshima Univ., Hiroshima, Japan; National Institute for Land and Infrastructure Management, Tsukuba, Japan; Building Research Institute, Tsukuba, Japan; Research Institute for Sustainable Humanosphere, Kyoto University, Kyoto, Japan | P38: Hatachi K., Graduate School of Advanced Science and Engineering, Hiroshima University, Hiroshima, Japan; Nishimiya W., Hiroshima Univ., Hiroshima, Japan; Mori T., Graduate School of Advanced Science and Engineering, Hiroshima University, Hiroshima, Japan; Araki Y., National Institute for Land and Infrastructure Management, Tsukuba, Japan; Sakashita M., Building Research Institute, Tsukuba, Japan; Nakashima S., Building Research Institute, Tsukuba, Japan; Isoda H., Research Institute for Sustainable Humanosphere, Kyoto University, Kyoto, Japan | Q38: Many studies have been conducted on timber-concrete composite systems (TCC) as a new technology for medium to large scale buildings using wood materials. This study focuses on CLT-reinforced concrete composite floors and aims to understand the long-term performance of TCC floors under fixed end support conditions through the bending creep tests. As the results of the bending creep test, the creep coefficient calculated using the power law is about 4, which is about four times smaller than the creep coefficient of concrete slab. In the both-ends fixed condition, it was shown different force condition compare the simply supported condition examined in prior studies, the top surface of the edge of the composite floor bears the tensile force, so that both the concrete and wood sections bear the tensile and compressive forces. Accordingly, the bending stiffness of the floor system was calculated using the formula proposed by FPInnovations based on the γ method, and a larger value was calculated than the experimental value. It was considered this difference due to cracking caused by the concrete bearing tensile forces and the consequent reduction in anchorage, so to understand the long-term behavior of this system is planned to investigate a cracking etc. in detail. © (2025) WORLD CONFERENCE ON TIMBER ENGINEERING 2025 (WCTE 2025) All rights reserved. | R38: Creep behavior; Cross-laminated timber; Floor; Timber- reinforced concrete composite | S38: Bending tests; Concrete slabs; Concrete testing; Cracks; Creep; Creep testing; Reinforced concrete; Timber; Wooden floors; Composite floors; Concrete composites; Creep behaviors; Cross laminated; Cross-laminated timber; Fixed ends; Laminated timber; Tensile forces; Timber- reinforced concrete composite; Timber-concrete composites; Laminated composites; Laminating | U38: Rischmiller K.; Saleem M.A.; Downey C.; Gattas J.; Hossy D.; Ottenhaus L.; Wu W.; Zhang Y.; Yan Z. | V38: World Conference on Timber Engineering (WCTE) | X38: 979-833132089-8 | AA38: English | AB38: Proc. from World Conf. Timber Eng.: Adv. Timber Future Built Environ., WCTE | AC38: Conference paper | AD38: Final | AF38: Scopus | AG38: 2-s2.0-105010273928
A39: Lamothe S.; Sorelli L.; Blanchet P.; Galimard P. | B39: 57216157064; 8833588000; 7102260600; 6506441067 | C39: Lightweight and slender timber-concrete composite floors made of CLT-HPC and CLT-UHPC with ductile notch connectors | D39: 2021 | E39: Engineering Structures | F39: 243 | H39: 112409 | L39: 29 | M39: 10.1016/j.engstruct.2021.112409 | N39: https://www.scopus.com/pages/publications/85111055521?origin=resultslist | O39: Département de Génie Civil, Université Laval, Québec, G1V 0A6, Canada; Department of Wood and Forest Sciences, Université Laval, Québec, G1V 0A6, Canada; Department of Construction Timber Engineering, University of Bordeaux, France | P39: Lamothe S., Département de Génie Civil, Université Laval, Québec, G1V 0A6, Canada; Sorelli L., Département de Génie Civil, Université Laval, Québec, G1V 0A6, Canada; Blanchet P., Department of Wood and Forest Sciences, Université Laval, Québec, G1V 0A6, Canada; Galimard P., Department of Construction Timber Engineering, University of Bordeaux, France | Q39: Cross-Laminated Timber (CLT) structures have been emerging worldwide for residential floors in multi-storey buildings thanks to their lightness, fast construction and low ecological footprint. This work aims at fostering this application, which is often limited by vibrational and deflection limits, by investigating composite slab floors made of CLT and High-Performance Concrete (HPC) slab as well as CLT and Ultra High-Performance Fiber Reinforced Concrete (UHPFRC). Firstly, the composite floors CLT-HPC and CLT-UHPFRC with a span of 8 m were designed by considering a multicriteria analysis. To assure a certain structural ductility, previously developed ductile notch connectors were employed. As an economic choice, no shear reinforcement in the concrete slab was employed. Then, full-scale composite beams were fabricated in order to verify the predicted flexural behaviour and natural frequency. A numerical analysis was carried out to verify the connectors could effectively yield before the timber collapse. The comparison between the numerical simulation and the slip measurements confirmed that about 50% of the notch connections fully yielded and underwent inelastic deformation which favors the structural ductility. In the case of the CLT-HPC floor, a reduction of the notch contact surface due to the use of plastic sheet waterproofing as well as shear cracks developing in the concrete close to the notch corner both reduced the expected structural stiffness. Finally, the CLT-UHPFRC floor is endowed with outstanding values of slenderness ratio (∼35) and lightness (∼2 kPa), while eliminating the use of shear reinforcement and sheet waterproofing. © 2021 Elsevier Ltd | R39: Cross Laminated Timber (CLT); Ductile Notch Connections; High Performance Concrete (HPC); Timber-concrete composite structures; Ultra-High Fiber Performance Concrete (UHPFRC) | S39: Concrete slabs; Ductility; Floors; Laminated composites; Laminating; Reinforced concrete; Timber; Waterproofing; Composite floors; Cross laminated; Cross laminated timber; Ductile notch connection; High performance concrete; High-performance concrete; Laminated timber; Timber-concrete composite structures; Ultra-high; Ultra-high fiber performance concrete; comparative study; composite; ductility; floor; numerical method; reinforced concrete; timber; High performance concrete | T39: L. Sorelli; Département de Génie Civil, Université Laval, Québec, G1V 0A6, Canada; email: luca.sorelli@gci.ulaval.ca | V39: Elsevier Ltd | W39: 1410296 | Y39: ENSTD | AA39: English | AB39: Eng. Struct. | AC39: Article | AD39: Final | AE39: All Open Access; Green Open Access | AF39: Scopus | AG39: 2-s2.0-85111055521
A40: Shahnewaz M.; Jackson R.; Tannert T. | B40: 55634928200; 57193120662; 22939744900 | C40: Cross-Laminated Timber Concrete Composite Systems for Long-Span Floors | D40: 2022 | E40: Structures Congress 2022 - Selected Papers from the Structures Congress 2022 | I40: 356 | J40: 363 | K40: =scopus[[#This Row],[Page end]]-scopus[[#This Row],[Page start]] -> 7 | L40: 0 | M40: 10.1061/9780784484180.030 | N40: https://www.scopus.com/pages/publications/85129123477?origin=resultslist | O40: Fast + Epp, Vancouver, Canada; UNBC, Prince George, Canada | P40: Shahnewaz M., Fast + Epp, Vancouver, Canada; Jackson R., Fast + Epp, Vancouver, Canada; Tannert T., UNBC, Prince George, Canada | Q40: Experimental investigations on full-scale (9.6 m) and half-scale (4.8 m) cross-laminated timber (CLT)-concrete-composite (TCC) slab bands are presented. The out-of-plane shear and ultimate flexural capacities of these TCC floors utilizing several types of shear connectors were determined. The TCC system was comprised of a 245 mm thick, 7-ply CLT with 150 mm concrete topping joined with shear connectors. The efficiency of three types of shear connectors: self-tapping screws, steel kerf plates, and proprietary glued-in Holz-Beton-Verbund (HBV) connectors was evaluated. Six series of floor systems, one control series of raw CLT floors (without concrete topping) and five TCC series, were tested for a total of 6-half scale control slabs, 18-half scale, and 6-full scale TCC slabs were tested under four-point bending. The results from this research were utilized to make project-specific design decisions for "The Arbour,"a 10-storey mass timber building for George Brown College, located in Toronto, Canada. © ASCE. | S40: Concretes; Floors; Laminated composites; Timber; Wooden buildings; Concrete composites; Cross laminated; Experimental investigations; Laminated timber; Long span; Out-of-plane shear; Shear connector; Timber-concrete composite slabs; Timber-concrete composites; Ultimate flexural capacity; Laminating | U40: Soules J.G. | V40: American Society of Civil Engineers (ASCE) | X40: 978-078448418-0 | AA40: English | AB40: Struct. Congr. - Sel. Pap. Struct. Congr. | AC40: Conference paper | AD40: Final | AF40: Scopus | AG40: 2-s2.0-85129123477
A41: Kang Y.; Kim S. | B41: 56122043500; 59722174400 | C41: Carbon mitigation and energy efficiency of hybrid cross-laminated timber buildings: A case study on a community center design | D41: 2025 | E41: Energy and Buildings | F41: 345 | H41: 116060 | L41: 4 | M41: 10.1016/j.enbuild.2025.116060 | N41: https://www.scopus.com/pages/publications/105009328797?origin=resultslist | O41: Department of Architecture and Architectural Engineering, Yonsei University, Seoul, 03722, South Korea | P41: Kang Y., Department of Architecture and Architectural Engineering, Yonsei University, Seoul, 03722, South Korea; Kim S., Department of Architecture and Architectural Engineering, Yonsei University, Seoul, 03722, South Korea | Q41: Achieving carbon neutrality in the building sector requires innovative materials such as cross-laminate timber (CLT), energy-efficient solutions, renewable energy, and advanced building technologies to reduce greenhouse gas (GHG) emissions and enhance efficiency. This study evaluates the carbon mitigation potential of CLT as a nature-based solution (NBS) through substitution scenarios in a small-scale regional community center. The process begins with identifying potential building materials and a baseline model using traditional concrete. CLT is integrated as a hybrid material for walls and floors, substituting concrete in varying ratios to evaluate the life cycle carbon emissions and energy efficiency improvements. Key stages of the life cycle assessment (LCA) include material production, construction, operation, and end-of-life. Substituting concrete with CLT reduces GHG emissions by up to 9.22%, with the product stage showing the highest potential for carbon mitigation. The use stage also demonstrates significant reductions owing to the superior thermal performance of CLT, particularly in terms of operational energy consumption, where heating accounts for 88% of the energy savings in cold climates. Additionally, the study highlights the benefits of extending building lifespans and integrating renewable energy during the operation phase. Hybrid CLT buildings with higher exterior substitution ratios, as seen in scenarios S3-1 and S3-2, exhibit notable improvements in energy efficiency and life cycle emissions. Unlike previous studies, this study provides a focused analysis of the substitution rates, serving as a foundation for future large-scale timber construction. Continued research on detailed assemblies and optimized low-carbon designs is essential for advancing sustainable high-rise timber construction. © 2025 Elsevier B.V. | R41: Carbon neutrality; Cross-laminated timber; Energy efficiency; Hybrid timber construction; Life cycle assessment | S41: Architectural design; Carbon; Carbon cycle; Construction industry; Ecodesign; Energy utilization; Green buildings; Greenhouse gases; Hybrid materials; Laminating; Life cycle; Life cycle assessment; Structural design; Timber; Zero-carbon; Carbon energy; Carbon mitigation; Carbon neutralities; Cross laminated; Cross-laminated timber; Energy; Hybrid timber construction; Laminated timber; Timber buildings; Timber construction; Energy efficiency | T41: S. Kim; Department of Architecture and Architectural Engineering, Yonsei University, Seoul, 03722, South Korea; email: kimsumin@yonsei.ac.kr | V41: Elsevier Ltd | W41: 3787788 | Y41: ENEBD | AA41: English | AB41: Energy Build. | AC41: Article | AD41: Final | AF41: Scopus | AG41: 2-s2.0-105009328797
A42: Renedo C.M.C.; Rosso M.M.; Chillitupa-Palomino L.; Aloisio A.; Díaz I.M. | B42: 57211252051; 57222257965; 59245169100; 57205733998; 14051891600 | C42: Dynamic Characterization and Vibration Serviceability Assessment of Two Bare High-Frequency CLT Floors | D42: 2025 | E42: Lecture Notes in Civil Engineering | F42: 676 LNCE | I42: 583 | J42: 592 | K42: =scopus[[#This Row],[Page end]]-scopus[[#This Row],[Page start]] -> 9 | L42: 0 | M42: 10.1007/978-3-031-96114-4_60 | N42: https://www.scopus.com/pages/publications/105019183955?origin=resultslist | O42: Department of Continuum Mechanics and Theory of Structures, ETSI Caminos, Canales y Puertos, Universidad Politécnica de Madrid, Madrid, Spain; Department of Structural, Geotechnical and Building Engineering, Politecnico di Torino, Turin, Italy; Department of Civil, Construction-Architectural and Environmental Engineering, University of L’Aquila, L’Aquila, Italy | P42: Renedo C.M.C., Department of Continuum Mechanics and Theory of Structures, ETSI Caminos, Canales y Puertos, Universidad Politécnica de Madrid, Madrid, Spain; Rosso M.M., Department of Structural, Geotechnical and Building Engineering, Politecnico di Torino, Turin, Italy; Chillitupa-Palomino L., Department of Continuum Mechanics and Theory of Structures, ETSI Caminos, Canales y Puertos, Universidad Politécnica de Madrid, Madrid, Spain; Aloisio A., Department of Civil, Construction-Architectural and Environmental Engineering, University of L’Aquila, L’Aquila, Italy; Díaz I.M., Department of Continuum Mechanics and Theory of Structures, ETSI Caminos, Canales y Puertos, Universidad Politécnica de Madrid, Madrid, Spain | Q42: The building construction industry currently represents around 11% of the global carbon emissions. Thus, nowadays the widespread use of low-carbon footprint materials such as timber is considered a priority within the sector. Timber buildings have shown adequate structural performance in terms of capacity and stiffness; however, their extremely lightweight nature makes them more prone to develop excessive vibration responses. This fact is especially remarkable in modern buildings mainly built with engineering wooden products (EWPs) such as Cross Laminated Timber (CLT). Focusing on timber floors, their vibration serviceability limit state (VSLS) usually consists of limiting their dynamic response to human-induced loads as those produced when walking or performing aerobic activities. During the last three decades, the study of floors’ VSLS has been developed in parallel by two methodological schools, that of concrete/composite floors and that of timber ones. New Eurocode 5 has faced this inconsistency by updating its vibration-checking method, moving closer to the approaches used for concrete ones. However, there is still some controversy regarding these new vibration limits and the way of analyzing the response of lightweight floors with natural frequencies over 15 Hz. This paper provides an additional case study on the literature, in which two high-frequency CLT floors have been dynamically characterized using operational modal analysis. Additionally, a subsequent experimental assessment of their VSLS has been performed. The results shed light on the dynamic behavior of these types of floors increasingly used in the building construction sector. © The Author(s), under exclusive license to Springer Nature Switzerland AG 2025. | R42: CLT floors; Floor Vibrations; Timber buildings; Vibration Serviceability | S42: Concretes; Construction; Construction industry; Dynamic response; Modal analysis; Structural dynamics; Structural Mechanics; Timber; Vibration analysis; Wooden floors; Cross laminated; Cross laminated timber floor; Dynamic vibration; Floor vibrations; High frequency HF; Laminated timber; Serviceability limit state; Timber buildings; Timber floors; Vibration serviceability; Wooden buildings | T42: C.M.C. Renedo; Department of Continuum Mechanics and Theory of Structures, ETSI Caminos, Canales y Puertos, Universidad Politécnica de Madrid, Madrid, Spain; email: carlos.martindelaconcha@upm.es | U42: Cunha A.; Caetano E. | V42: Springer Science and Business Media Deutschland GmbH | W42: 23662557 | X42: 978-303196113-7 | AA42: English | AB42: Lect. Notes Civ. Eng. | AC42: Conference paper | AD42: Final | AF42: Scopus | AG42: 2-s2.0-105019183955
A43: Roncari A.; Gobbi F.; Loss C. | B43: 57221464654; 57204964831; 37098919100 | C43: Nonlinear static seismic response of a building equipped with hybrid cross-laminated timber floor diaphragms and concentric X-braced steel frames | D43: 2021 | E43: Buildings | F43: 11 | G43: 1 | H43: 9 | I43: 1 | J43: 17 | K43: =scopus[[#This Row],[Page end]]-scopus[[#This Row],[Page start]] -> 16 | L43: 12 | M43: 10.3390/buildings11010009 | N43: https://www.scopus.com/pages/publications/85099203594?origin=resultslist | O43: Sustainable Engineered Structural Solutions Laboratory, Department of Wood Science, The University of British Columbia, Vancouver, V6T 1Z4, BC, Canada; Department of Civil, Environmental and Mechanical Engineering, University of Trento, Trento, 38122, Italy | P43: Roncari A., Sustainable Engineered Structural Solutions Laboratory, Department of Wood Science, The University of British Columbia, Vancouver, V6T 1Z4, BC, Canada, Department of Civil, Environmental and Mechanical Engineering, University of Trento, Trento, 38122, Italy; Gobbi F., Department of Civil, Environmental and Mechanical Engineering, University of Trento, Trento, 38122, Italy; Loss C., Sustainable Engineered Structural Solutions Laboratory, Department of Wood Science, The University of British Columbia, Vancouver, V6T 1Z4, BC, Canada | Q43: Simplified seismic design procedures mostly recommend the adoption of rigid floor diaphragms when forming a building’s lateral force-resisting structural system. While rigid behavior is compatible with many reinforced concrete or composite steel-concrete floor systems, the intrinsic stiffness properties of wood and ductile timber connections of timber floor slabs typically make reaching a such comparable in-plane response difficult. Codes or standards in North America widely cover wood-frame construction, with provisions given for both rigid and flexible floor diaphragms designs. Instead, research is ongoing for emerging cross-laminated-timber (CLT) and hybrid CLT-based technologies, with seismic design codification still currently limited. This paper deals with a steel-CLT-based hybrid structure built by assembling braced steel frames with CLT-steel composite floors. Preliminary investigation on the performance of a 3-story building under seismic loads is presented, with particular attention to the influence of in-plane timber diaphragms flexibility on the force distribution and lateral deformation at each story. The building complies with the Italian Building Code damage limit state and ultimate limit state design requirements by considering a moderate seismic hazard scenario. Nonlinear static analyses are performed adopting a finite-element model calibrated based on experimental data. The CLT-steel composite floor in-plane deformability shows mitigated effects on the load distribution into the bracing systems compared to the ideal rigid behavior. On the other hand, the lateral deformation always rises at least 17% and 21% on average, independently of the story and load distribution along the building’s height. © 2020 by the authors. Licensee MDPI, Basel, Switzerland. | R43: Cross-laminated timber (CLT); Hybrid structures; Lateral resistance; Load distribution; Mass timber construction; Pushover analysis; Seismic performance; Semi-rigid diaphragms | T43: C. Loss; Sustainable Engineered Structural Solutions Laboratory, Department of Wood Science, The University of British Columbia, Vancouver, V6T 1Z4, Canada; email: cristiano.loss@ubc.ca | V43: MDPI AG | W43: 20755309 | AA43: English | AB43: Buildings | AC43: Article | AD43: Final | AE43: All Open Access; Gold Open Access; Green Open Access | AF43: Scopus | AG43: 2-s2.0-85099203594
A44: Himes A.; Busby G. | B44: 56096757800; 57371204400 | C44: Wood buildings as a climate solution | D44: 2020 | E44: Developments in the Built Environment | F44: 4 | H44: 100030 | L44: 132 | M44: 10.1016/j.dibe.2020.100030 | N44: https://www.scopus.com/pages/publications/85104589661?origin=resultslist | O44: Mississippi State University Department of Forestry, United States; GreenWood Resources, Inc, United States | P44: Himes A., Mississippi State University Department of Forestry, United States; Busby G., GreenWood Resources, Inc, United States | Q44: We conducted a systematic literature search and meta-analysis of studies with side-by-side life cycle analysis comparisons of mid-rise buildings using mass timber and conventional, concrete and steel, building materials. Based on 18 comparisons across four continents, we found that substituting conventional building materials for mass timber reduces construction phase emissions by 69%, an average reduction of 216 kgCO2e/m2 of floor area. Studies included in our analysis were unanimous in showing emissions reductions when building with mass timber compared to conventional materials. Scaling-up low-carbon construction, assuming mass timber is substituted for conventional building materials in half of expected new urban construction, could provide as much as 9% of global emissions reduction needed to meet 2030 targets for keeping global warming below 1.5 ​°C. Realizing the climate mitigation potential of mass timber building could be accelerated by policy and private investment. Policy actions such as changing building codes, including mass timber in carbon offset crediting programs and setting building-sector-specific emissions reduction goals will remove barriers to and incentivize the adoption of mass timber. Private capital, as debt or equity investment, is poised to play a crucial role in financing mass timber building. © 2020 The Author(s) | R44: Carbon; CLT; Cross laminated timber; Global warming; LCA; Mass timber | S44: Building codes; Building materials; Carbon; Emission control; Global warming; Life cycle; Timber; Wooden buildings; Climate mitigations; Construction phase; Conventional materials; Emissions reduction; Life cycle analysis; Low carbon constructions; Private investment; Urban construction; Construction | T44: A. Himes; Starkville, 311 San Marcos, 39759, United States; email: austin.himes@msstate.edu | V44: Elsevier Ltd | W44: 26661659 | AA44: English | AB44: Dev. Built. Environ. | AC44: Article | AD44: Final | AE44: All Open Access; Gold Open Access; Green Open Access | AF44: Scopus | AG44: 2-s2.0-85104589661
A45: Ellrich E.R.; Via B.; Roueche D.; Sener K. | B45: 59663758500; 6603289572; 55365701900; 55366144500 | C45: A Comparative Floor Assembly Design and Life-Cycle Assessment Study of Steel–Timber and Steel–Concrete Composite Structural Systems | D45: 2025 | E45: Forest Products Journal | F45: 75 | G45: 1 | I45: 82 | J45: 94 | K45: =scopus[[#This Row],[Page end]]-scopus[[#This Row],[Page start]] -> 12 | L45: 0 | M45: 10.13073/FPJ-D-24-00041 | N45: https://www.scopus.com/pages/publications/85219498242?origin=resultslist | O45: KPFF Structural Consultants, Salt Lake City, UT, United States; College of Forestry, Wildlife, and Environment, United States; Dept. of Civil and Environmental Engineering, United States; Auburn University, Auburn, AL, United States | P45: Ellrich E.R., KPFF Structural Consultants, Salt Lake City, UT, United States; Via B., College of Forestry, Wildlife, and Environment, United States; Roueche D., Dept. of Civil and Environmental Engineering, United States; Sener K., Auburn University, Auburn, AL, United States | Q45: Steel-timber composite (STC) structures, which utilize mass-timber cross-laminated-timber (CLT) floor panels compositely connected to steel framing, have emerged as a viable alternative structural system with a low carbon footprint along with potential improvements in the structural performance and constructability against traditional steel–concrete (SCC) systems. This paper focuses on the floor assembly design and sustainability aspect of STC systems relative to SCC systems with particular emphasis on results from a comparative whole-building life-cycle-assessment study conducted on functionally equivalent STC and SCC office buildings at 7 and 18 stories. Embodied carbon was lower in the STC systems since the total embodied carbon reduced by 50 and 42 percent in the 7- and 18-story structures, respectively. Embodied fossil energy was also lower in the STC systems since the total embodied fossil energy reduced by 32 and 21 percent in the 7- and 18-story structures, respectively. Sensitivity studies on biogenic carbon inclusion have shown substantial impact on the results. ©Forest Products Society 2025. | S45: Assembly; Carbon; Design; Energy; Life; Steel; Structures; Systems; Carbon footprint; Concretes; Laminated composites; Timber; Wooden floors; Assembly designs; Composite structural systems; Composites structures; Concrete system; Cross laminated; Embodied carbons; Fossil energy; Laminated timber; Steel concrete; Steel-concrete composite; Office buildings | T45: D. Roueche; Dept. of Civil and Environmental Engineering, United States; email: dbr0011@auburn.edu; K. Sener; Auburn University, Auburn, United States; email: sener@auburn.edu | V45: Forest Products Society | W45: 157473 | Y45: FPJOA | AA45: English | AB45: For Prod J | AC45: Article | AD45: Final | AF45: Scopus | AG45: 2-s2.0-85219498242
A46: Hiramitsu A.; Hirakawa S. | B46: 36499616500; 56637881700 | C46: INFLUENCE OF DRY-TYPE DOUBLE FLOOR STRUCTURE ON FLOOR IMPACT SOUND INSULATION PERFORMANCE | D46: 2023 | E46: Proceedings of the International Congress on Sound and Vibration | L46: 0 | N46: https://www.scopus.com/pages/publications/85170643192?origin=resultslist | O46: Department of Environmental Engineering, Building Research Institute, Ibaraki, Japan; National Institute for Land and Infrastructure Management, Ibaraki, Japan | P46: Hiramitsu A., Department of Environmental Engineering, Building Research Institute, Ibaraki, Japan; Hirakawa S., National Institute for Land and Infrastructure Management, Ibaraki, Japan | Q46: The dry-type double floor structure is often constructed on floor slabs as the floor finishing material for concrete apartment houses in Japan. This floor structure consists of a support footing with anti-vibration rubber, particle board, asphalt-based sound insulation sheets, flooring, and other top surface materials. In the case of the concrete building, the floor finishing material is effective for the light-weight floor impact sound insulation performance, however, it is not effective for the heavy-weight floor impact sound insulation performance. This is believed to the due to the mass-spring resonance of the air layer and the top surface. For the Cross Laminated Timber (CLT) building, the floor finishing material is effective for both the light-weight and the heavy-weight floor impact sound insulation performance hence the floor finishing material works differently with the different buildings. But no data was obtained from the same product installed on the different floor structures. The reduction of the transmitted floor impact sound level due to the same dry-type double floor structure was investigated with different constructions. The laboratory experiments were conducted in the CLT experimental building, a 6-storey wood-frame construction experimental building and vertical transmission suite in BRI Japan. Those are the 210 mm CLT bare floor, 210 mm CLT floor with floating floor and composite 210 mm CLT and 100 mm concrete floor and 200 mm concrete bare floor. As a result, the reduction of transmitted floor impact sound level changes depending on the driving-point impedance. The higher the driving-point impedance, the smaller the reduction of transmitted floor impact sound level was obtained. © 2023 Proceedings of the International Congress on Sound and Vibration. All rights reserved. | R46: Cross Laminated Timber; driving-point impedance; dry-type double floor structure; floor impact sound insulation; reduction of transmitted impact sound by floor coverings | S46: Acoustic Insulation; Concrete; Impact; Lamination; Performance; Rubber; Weight; Acoustic waves; Apartment houses; Concrete slabs; Electric circuit breakers; Laminated composites; Laminating; Rubber; Timber; Wooden floors; % reductions; Cross laminated; Cross laminated timber; Driving point impedances; Dry types; Dry-type double floor structure; Floor covering; Floor impact sound insulation; Floor structures; Floor-impact sound; Impact sound; Impact sound insulation; Laminated timber; Reduction of transmitted impact sound by floor covering; Sound insulation | U46: Carletti E. | V46: Society of Acoustics | W46: 23293675 | X46: 978-801103423-8 | AA46: English | AB46: Proc. Int. Congr. Sound Vib. | AC46: Conference paper | AD46: Final | AF46: Scopus | AG46: 2-s2.0-85170643192
A47: Lamothe S.; Sorelli L.; Blanchet P.; Galimard P. | B47: 57216157064; 8833588000; 7102260600; 6506441067 | C47: Engineering ductile notch connections for composite floors made of laminated timber and high or ultra-high performance fiber reinforced concrete | D47: 2020 | E47: Engineering Structures | F47: 211 | H47: 110415 | L47: 36 | M47: 10.1016/j.engstruct.2020.110415 | N47: https://www.scopus.com/pages/publications/85082662497?origin=resultslist | O47: Département de Génie Civil, Université Laval, G1V 0A6, Québec, Canada; Department of Wood and Forest Sciences, Université Laval, G1V 0A6, Québec, Canada; Institut d'Ingénierie et de Mécanique, Université de Bordeaux, France | P47: Lamothe S., Département de Génie Civil, Université Laval, G1V 0A6, Québec, Canada; Sorelli L., Département de Génie Civil, Université Laval, G1V 0A6, Québec, Canada; Blanchet P., Department of Wood and Forest Sciences, Université Laval, G1V 0A6, Québec, Canada; Galimard P., Institut d'Ingénierie et de Mécanique, Université de Bordeaux, France | Q47: Different kinds of ductile connectors have been lately developed for enhancing the structural ductility of Timber-Concrete Composite (TCC) structures. In particular, ductile notch connections can be designed by favoring the local compression failure of wood fibers. This work aims at further developing economic and ductile notch connector by considering different floor systems made of Glulam Laminated Timber (GLT) beam or Cross Laminated Timber (GLT or CLT) slab connected with a High Performance Concrete (HPC) slab or a Ultra-High Performance Fiber Reinforced Concrete (UHPFRC) slab. Firstly, the geometry of the notch connector was suitably designed for favoring a ductile hierarchy of collapse modes. Then, a wide campaign of push-out tests was carried out to characterize the shear behaviour of 14 connection configurations by varying the notch geometry, the concrete type and the possible presence of acoustic insulation. Finally, based on the experimentally identified connection shear law, an example of design is presented for a TCC slab of 9 m span. The insulation layer was found to reduce the connection stiffness, but to increases the structural stiffness thanks to the enhanced lever arm of the composite action. For plastically designed TCC structures, the connection ductility allows increasing the structural ductility for both GLT-(U)HPC and for CLT-(U)UPC floor systems. © 2020 Elsevier Ltd | R47: Cross Laminated Timber (CLT); Glued Laminated Timber (GLT); High Performance Concrete (HPC); Timber-concrete composite structures; Ultra-High Performance Fiber Reinforced Concrete (UHPFRC) | S47: Composite structures; Concrete slabs; Ductility; Fiber reinforced concrete; Fibers; Floors; High performance concrete; Laminated composites; Laminating; Stiffness; Timber; Connection stiffness; Cross laminated; Glued-laminated timber; Structural ductility; Structural stiffness; Timber-concrete composite structures; Timber-concrete composites; Ultra-high-performance fiber-reinforced concrete; composite; ductility; floor; geometry; reinforced concrete; stiffness; timber; Failure (mechanical) | T47: L. Sorelli; Département de Génie Civil, Université Laval, G1V 0A6, Canada; email: luca.sorelli@gci.ulaval.ca | V47: Elsevier Ltd | W47: 1410296 | Y47: ENSTD | AA47: English | AB47: Eng. Struct. | AC47: Article | AD47: Final | AF47: Scopus | AG47: 2-s2.0-85082662497
A48: Chiniforush A.A.; Akbarnezhad A.; Valipour H.; Xiao J. | B48: 57190258599; 36730725400; 6508258428; 7402564490 | C48: Energy implications of using steel-timber composite (STC) elements in buildings | D48: 2018 | E48: Energy and Buildings | F48: 176 | I48: 203 | J48: 215 | K48: =scopus[[#This Row],[Page end]]-scopus[[#This Row],[Page start]] -> 12 | L48: 67 | M48: 10.1016/j.enbuild.2018.07.038 | N48: https://www.scopus.com/pages/publications/85050815852?origin=resultslist | O48: Centre for Infrastructure Engineering and Safety, School of Civil and Environmental Engineering, University of New South Wales, Sydney, Australia; School of Civil Engineering, The University of Sydney, NSW 2006, Australia; Department of Structural Engineering, College of Civil Engineering, Tongji University, China | P48: Chiniforush A.A., Centre for Infrastructure Engineering and Safety, School of Civil and Environmental Engineering, University of New South Wales, Sydney, Australia; Akbarnezhad A., School of Civil Engineering, The University of Sydney, NSW 2006, Australia; Valipour H., Centre for Infrastructure Engineering and Safety, School of Civil and Environmental Engineering, University of New South Wales, Sydney, Australia; Xiao J., Department of Structural Engineering, College of Civil Engineering, Tongji University, China | Q48: Among different structural elements, floor elements account for the largest portion of the mass and thus the embodied energy of the structures. Therefore, a viable approach to reduce the embodied energy of buildings may involve replacing the conventional floor systems with alternative low embodied energy floor systems. This paper investigates the potential reductions in the life cycle energy of the steel structures achievable through the adoption of steel-timber composite (STC) elements as floor and shear wall systems. Evaluating the life cycle energy implications of adopting STC elements is especially important due to the trade-off between their positive and negative effects on embodied energy and operating energy, respectively, when compared to alternative conventional elements with a higher thermal mass including concrete and steel elements. The life-cycle energy of four different structures designed for a building is evaluated by accounting for energy use in material extraction and processing, component manufacturing, transportation, construction, operation and end of life phases. Two steel structures with STC and steel-concrete composite floors and concrete shear walls are considered to evaluate the effects of STC floors on the energy-usage footprint. The third structure is designed with STC floor system and CLT shear walls; and the fourth structure is designed as a concrete structure to provide a basis for comparison between energy footprint of steel structures with STC and reinforced concrete structures. The results indicate that when designing the building with a steel structure, adoption of STC floor and shear wall systems resulted in 107.5% decrease in the embodied energy at the expense of only a slight increase in the operating energy. Furthermore, adopting a steel structure with STC floors was found to result in considerable life cycle energy savings, viz. 895 MJ/m2, when compared with the same building designed with a concrete structure. © 2018 Elsevier B.V. | R48: Buildings; Concrete structure; Cross laminated timber (clt); Embodied energy; Life cycle energy; Steel structure; Steel-timber composite (stc) elements | S48: Buildings; Concrete buildings; Concrete construction; Economic and social effects; Energy conservation; Floors; Laminated composites; Materials handling; Reinforced concrete; Shear flow; Shear walls; Steel structures; Timber; Component manufacturing; Concrete shear wall; Cross laminated; Embodied energy; Life cycle energies; Positive and negative effect; Steel-concrete composite floor; Structural elements; Life cycle | T48: A. Akbarnezhad; School of Civil Engineering, The University of Sydney, NSW 2006, Australia; email: ali.nezhad@sydney.edu.au | V48: Elsevier Ltd | W48: 3787788 | Y48: ENEBD | AA48: English | AB48: Energy Build. | AC48: Article | AD48: Final | AE48: All Open Access; Green Open Access | AF48: Scopus | AG48: 2-s2.0-85050815852
A49: Shahnewaz M.; Jackson R.; Tannert T. | B49: 55634928200; 57193120662; 22939744900 | C49: Experimental dataset for effective bending stiffness and load-carrying capacity of CLT-concrete composite floor systems | D49: 2025 | E49: Data in Brief | F49: 63 | H49: 112170 | L49: 1 | M49: 10.1016/j.dib.2025.112170 | N49: https://www.scopus.com/pages/publications/105020989511?origin=resultslist | O49: Fast + Epp, Vancouver, BC, Canada; School of Engineering, University of Northern British Columbia, Prince George, Canada | P49: Shahnewaz M., Fast + Epp, Vancouver, BC, Canada; Jackson R., Fast + Epp, Vancouver, BC, Canada; Tannert T., School of Engineering, University of Northern British Columbia, Prince George, Canada | Q49: This article presents the dataset from experimental investigations on cross-laminated timber (CLT) concrete composite (TCC) floor systems. The data was collected at the University of Northern British Columbia, BC, Canada, for project-specific design decisions for “Limberlost Place”, a mass timber building for George Brown College, in Toronto, Canada designed by Fast + Epp, Vancouver, BC, Canada. The TCC systems comprised of 245 mm thick, 7-ply CLT panels with 150 mm concrete topping. A total of 18 small-scale shear connections, and 24 half-scale (4.6 m long) and 9 full-scale (9.2 m long) floors were tested. The dataset provides information on the effective bending stiffness and load-carrying capacity of long span beamless CLT-concrete floor systems. This data will also serve as essential inputs for engineers and researchers in modelling and design processes. Copyright © 2025. Published by Elsevier Inc. | R49: Composite floor; Cross-laminated timber; Timber connections; Timber floor | S49: Architectural design; Concrete slabs; Laminated composites; Laminating; Loads (forces); Stiffness; Structural design; Timber; Wooden buildings; Wooden floors; Bending load; Composite floors; Cross laminated; Cross-laminated timber; Effective bending stiffness; Laminated timber; Load carrying; Timber connections; Timber floors; Timber-concrete composites; Copyrights | T49: M. Shahnewaz; Fast + Epp, Vancouver, Canada; email: mshahnewaz@fastepp.com | V49: Elsevier Inc. | W49: 23523409 | AA49: English | AB49: Data Brief | AC49: Article | AD49: Final | AE49: All Open Access; Gold Open Access; Green Open Access | AF49: Scopus | AG49: 2-s2.0-105020989511
A50: Shahnewaz M.; Jackson R.; Tannert T. | B50: 55634928200; 57193120662; 22939744900 | C50: Reinforced cross-laminated timber-concrete composite floor systems | D50: 2023 | E50: Engineering Structures | F50: 291 | H50: 116395 | L50: 9 | M50: 10.1016/j.engstruct.2023.116395 | N50: https://www.scopus.com/pages/publications/85161706599?origin=resultslist | O50: Fast+Epp, 300 – 397 W 7th Avenue, Vancouver, V5Y 1M2, BC, Canada; School of Engineering, University of Northern British Columbia, Prince George, Canada | P50: Shahnewaz M., Fast+Epp, 300 – 397 W 7th Avenue, Vancouver, V5Y 1M2, BC, Canada; Jackson R., Fast+Epp, 300 – 397 W 7th Avenue, Vancouver, V5Y 1M2, BC, Canada; Tannert T., School of Engineering, University of Northern British Columbia, Prince George, Canada | Q50: This paper presents full-scale experimental investigations on cross-laminated timber concrete composite (TCC) systems. The primary objective was to determine the stiffness, ultimate load-carrying capacity, and failure modes of TCC systems using three different shear connectors: self-tapping screws, steel kerf plates, and proprietary glued-in perforated steel plates. The secondary objective was to determine the effectiveness of shear reinforcement in the CLT panels. The TCC system was comprised of 245 mm thick, 7-ply CLT panels with a 150 mm concrete topping. A total of 24 half-span (4.6 m long) and 9 full-span (9.2 m long) CLT and TCC floor segments were tested under symmetric four-point bending as well as torsional bending. For all test series, the CLT panels were either unreinforced, or reinforced using self-tapping screws. The shear reinforcement increased rolling shear capacity which helped to avoid CLT shear failure. Adding the concrete topping increased the shear capacity by up to 167%. The tests showed that the floors with steel kerf plates exhibited the highest capacity and stiffness, while also being the most easy-to-install solution. The results from this research guided project-specific design decisions for “Limberlost Place”, a mass timber building for George Brown College, in Toronto, Canada. © 2023 Elsevier Ltd | R50: Connections; Cross-laminated timber; Shear capacity; Structural composite | S50: Canada; Ontario [Canada]; Toronto; Concrete slabs; Laminated composites; Laminating; Plates (structural components); Reinforcement; Screws; Stiffness; Timber; Composite floor systems; Connection; Cross laminated; Cross-laminated timber; Laminated timber; Self-tapping screws; Shear capacity; Shear reinforcement; Structural composites; Timber-concrete composites; composite; concrete structure; dynamic response; multistorey building; shear strength; structural response; Floors | T50: T. Tannert; School of Engineering, University of Northern British Columbia, Prince George, Canada; email: thomas.tannert@unbc.ca | V50: Elsevier Ltd | W50: 1410296 | Y50: ENSTD | AA50: English | AB50: Eng. Struct. | AC50: Article | AD50: Final | AF50: Scopus | AG50: 2-s2.0-85161706599
A51: Albogami R.; Alotaibi D.; Althuwaiqeb S.; Alnassir F.; Alfaihani H.; Ahmed D.; Chowdhury S.; Ayadat T.; Khasawneh M.A. | B51: 59748641500; 59559541700; 57655768900; 59748334400; 59747873600; 57217208973; 36143739500; 20435579500; 57201650752 | C51: Sustainability and cost of a multi-story edifice, with CLT and LGS light weight floor system, at Neom-The Line | D51: 2025 | E51: Materials Research Proceedings | F51: 48 | I51: 113 | J51: 122 | K51: =scopus[[#This Row],[Page end]]-scopus[[#This Row],[Page start]] -> 9 | L51: 1 | M51: 10.21741/9781644903414-13 | N51: https://www.scopus.com/pages/publications/105003146284?origin=resultslist | O51: Department of Civil Engineering, Prince Mohammad Bin Fahd University, Al Khobar, Saudi Arabia | P51: Albogami R., Department of Civil Engineering, Prince Mohammad Bin Fahd University, Al Khobar, Saudi Arabia; Alotaibi D., Department of Civil Engineering, Prince Mohammad Bin Fahd University, Al Khobar, Saudi Arabia; Althuwaiqeb S., Department of Civil Engineering, Prince Mohammad Bin Fahd University, Al Khobar, Saudi Arabia; Alnassir F., Department of Civil Engineering, Prince Mohammad Bin Fahd University, Al Khobar, Saudi Arabia; Alfaihani H., Department of Civil Engineering, Prince Mohammad Bin Fahd University, Al Khobar, Saudi Arabia; Ahmed D., Department of Civil Engineering, Prince Mohammad Bin Fahd University, Al Khobar, Saudi Arabia; Chowdhury S., Department of Civil Engineering, Prince Mohammad Bin Fahd University, Al Khobar, Saudi Arabia; Ayadat T., Department of Civil Engineering, Prince Mohammad Bin Fahd University, Al Khobar, Saudi Arabia; Khasawneh M.A., Department of Civil Engineering, Prince Mohammad Bin Fahd University, Al Khobar, Saudi Arabia | Q51: Climate change and global warming, driven primarily by human activities, are urgent global issues necessitating immediate attention and action. The construction sector, responsible for nearly 40% of global greenhouse gas emissions, plays a critical role in these challenges. This study focuses on designing a sustainable multi-story edifice at Neom-The Line using cross-laminated timber (CLT) and light gauge steel (LGS) as lightweight floor systems. By comparing the carbon emissions of a CLT-hybrid building and an LGS-hybrid building, the study demonstrates the potential of sustainable materials in reducing CO2 emissions. Results indicate that the CLT-hybrid structure emits significantly less CO2 compared to the LGS-hybrid and traditional reinforced concrete (RCC) structures. The incorporation of photovoltaic (PV) glass further enhances the sustainability of these buildings. This research aligns with the United Nations' Sustainable Development Goals and Saudi Vision 2030, promoting sustainable construction practices and contributing to climate action. © 2025, Association of American Publishers. All rights reserved. | R51: Carbon Emission; Cross-Laminated Timber (CLT); Hybrid Building; Light Gauge Steel (LGS); Neom-The Line; Sustainable Buildings | T51: D. Ahmed; Department of Civil Engineering, Prince Mohammad Bin Fahd University, Al Khobar, Saudi Arabia; email: dahmed@pmu.edu.sa | U51: Ayadat T. | V51: Association of American Publishers | W51: 24743941 | X51: 978-164490341-4 | AA51: English | AB51: Mater. Res. Proc. | AC51: Conference paper | AD51: Final | AE51: All Open Access; Hybrid Gold Open Access | AF51: Scopus | AG51: 2-s2.0-105003146284
A52: Hassanieh A.; Valipour H.R.; Bradford M.A. | B52: 57173189300; 6508258428; 7102411221 | C52: Composite connections between CLT slab and steel beam: Experiments and empirical models | D52: 2017 | E52: Journal of Constructional Steel Research | F52: 138 | I52: 823 | J52: 836 | K52: =scopus[[#This Row],[Page end]]-scopus[[#This Row],[Page start]] -> 13 | L52: 113 | M52: 10.1016/j.jcsr.2017.09.002 | N52: https://www.scopus.com/pages/publications/85029677033?origin=resultslist | O52: Centre for Infrastructure Engineering and Safety, School of Civil and Environmental Engineering, UNSW Sydney, 2052, NSW, Australia | P52: Hassanieh A., Centre for Infrastructure Engineering and Safety, School of Civil and Environmental Engineering, UNSW Sydney, 2052, NSW, Australia; Valipour H.R., Centre for Infrastructure Engineering and Safety, School of Civil and Environmental Engineering, UNSW Sydney, 2052, NSW, Australia; Bradford M.A., Centre for Infrastructure Engineering and Safety, School of Civil and Environmental Engineering, UNSW Sydney, 2052, NSW, Australia | Q52: A composite floor comprising of steel beams connected to cross laminated timber (CLT) panels is a sustainable alternative to composite floors with reinforced concrete slab. The structural performance of the steel-CLT floor depends strongly on the load-slip behaviour (particularly the stiffness and strength) of the shear connection between the steel beams and the CLT slabs. In this paper, the short-term behaviour of steel-CLT joints is studied by laboratory push-out experiments conducted on CLT-steel-CLT specimens, being analogous to familiar push tests on steel-concrete specimens. In addition to coach screws and bolts, a high-performance steel-CLT composite connection comprising of high-strength bolted shear connectors embedded in pockets of grout is proposed and tested. The push-out experiments are used to determine the load-slip, failure mode, stiffness and ultimate strength/capacity of the steel-CLT composite joints and to calibrate an empirical formula for the load-slip response of the CLT-to-steel connections. Furthermore, simple empirical formulae for the stiffness and ultimate capacity of the CLT-to-steel composite connections are proposed. © 2017 | R52: Bolted connectors; Cross laminated timber (CLT); Grouted connection; Push-out | S52: Bolts; Concrete slabs; Concretes; Floors; Grouting; Joints (structural components); Laminated composites; Laminating; Mortar; Reinforced concrete; Steel beams and girders; Stiffness; Timber; Composite connections; Cross laminated; Empirical formulas; Grouted connection; High performance steel; Push-out; Steel connections; Structural performance; High strength steel | T52: A. Hassanieh; Centre for Infrastructure Engineering and Safety, School of Civil and Environmental Engineering, UNSW Sydney, 2052, Australia; email: a.hassanieh@unsw.edu.au | V52: Elsevier Ltd | W52: 0143974X | AA52: English | AB52: J. Constr. Steel Res. | AC52: Article | AD52: Final | AF52: Scopus | AG52: 2-s2.0-85029677033
A53: Albino C.; Martins C.; Ferreira C.; Augusto R.; Dias A. | B53: 57199499536; 55546409400; 58717873600; 58608635700; 50760964400 | C53: MECHANICAL BEHAVIOUR OF NOTCH CONNECTION FOR MARITIME PINE CLT-CONCRETE COMPOSITE | D53: 2023 | E53: 13th World Conference on Timber Engineering, WCTE 2023 | F53: 5 | I53: 3121 | J53: 3126 | K53: =scopus[[#This Row],[Page end]]-scopus[[#This Row],[Page start]] -> 5 | L53: 0 | M53: 10.52202/069179-0406 | N53: https://www.scopus.com/pages/publications/85171799601?origin=resultslist | O53: University of Coimbra, ISISE, Department of Civil Engineering, Coimbra, Portugal; SerQ, Sertã, Portugal | P53: Albino C., University of Coimbra, ISISE, Department of Civil Engineering, Coimbra, Portugal; Martins C., University of Coimbra, ISISE, Department of Civil Engineering, Coimbra, Portugal; Ferreira C., SerQ, Sertã, Portugal; Augusto R., SerQ, Sertã, Portugal; Dias A., University of Coimbra, ISISE, Department of Civil Engineering, Coimbra, Portugal | Q53: Cross Laminated Timber (CLT) is one of the most representative Engineered Wood Products, especially for low- and mid-rise timber buildings. Although in the 2000s, its use in Europe increased significantly, Portugal is still at a starting point and Spain needs a boost for its dissemination. Aiming promotion and dissemination of this type of buildings in SUDOE region, Eguralt project promotes research and innovation capacity for its sustainable growth. As a partner, one of SerQ's objectives is to promote the production of CLT solutions with wood from local species. The advantages of CLT are well known. However, the use of CLT in composite solutions requires the study of the overall performance, namely: stiffness; strength; dynamics and acoustic performance. Continuing recent studies in these areas, this paper presents an experimental campaign on the assessment of CLT-concrete connections and its comparison with the design models available. CLT was produced at SerQ's facilities with local maritime pine (Pinus pinaster Ait.) wood. In situ concrete casting and precast concrete processes were a study variable. Notch shear connectors with different geometries and screws or U-shape rebar cages to prevent uplift, gives the system its composite behaviour. The load capacity of the connectors was theoretically predicted and validated with shear tests, and the experimental results were then compared with those. The results of the specimens cast in situ were satisfactory, while the results of the precast specimens were below expectations. © 13th World Conference on Timber Engineering, WCTE 2023. All rights reserved. | R53: CLT-concrete composite; composite floor; connection; experimental testing; maritime pine; shear test | S53: Concrete slabs; Precast concrete; Wood products; Composite floors; Connection; Cross laminated; Cross laminated timber-concrete composite; Experimental testing; Laminated timber; Maritime pines; Mechanical behavior; Shear tests; Timber-concrete composites; Timber | U53: Nyrud A.Q.; Malo K.A.; Nore K.; Alsen K.W.L.; Tulebekova S.; Staehr E.R.; Bergh G.; Wuyts W. | V53: World Conference on Timber Engineering (WCTE) | X53: 978-171387329-7 | AA53: English | AB53: World Conf. Timber Eng., WCTE | AC53: Conference paper | AD53: Final | AE53: All Open Access; Gold Open Access | AF53: Scopus | AG53: 2-s2.0-85171799601
A54: Lukić I.; Premrov M.; Leskovar Ž.V.; Passer A. | B54: 57220183396; 6701482772; 57220180180; 53875067300 | C54: Assessment of the environmental impact of timber and its potential to mitigate embodied GHG emissions | D54: 2020 | E54: IOP Conference Series: Earth and Environmental Science | F54: 588 | G54: 2 | H54: 22068 | L54: 13 | M54: 10.1088/1755-1315/588/2/022068 | N54: https://www.scopus.com/pages/publications/85097174625?origin=resultslist | O54: Faculty of Civil Engineering, Transportation Engineering, and Architecture, University of Maribor, Smetanova Ulica 17, Maribor, 2000, Slovenia; Working Group Sustainable Construction, Institute of Technology and Testing of Construction Materials, Graz University of Technology, Inffeldgasse 24, Graz, 8010, Austria | P54: Lukić I., Faculty of Civil Engineering, Transportation Engineering, and Architecture, University of Maribor, Smetanova Ulica 17, Maribor, 2000, Slovenia; Premrov M., Faculty of Civil Engineering, Transportation Engineering, and Architecture, University of Maribor, Smetanova Ulica 17, Maribor, 2000, Slovenia; Leskovar Ž.V., Faculty of Civil Engineering, Transportation Engineering, and Architecture, University of Maribor, Smetanova Ulica 17, Maribor, 2000, Slovenia; Passer A., Working Group Sustainable Construction, Institute of Technology and Testing of Construction Materials, Graz University of Technology, Inffeldgasse 24, Graz, 8010, Austria | Q54: Currently, the world is undergoing the biggest wave of urban growth in history. To accommodate this unprecedented growth, adding more than 230 billion m2 of new floor area to the global building stock by 2060 is expected. As embodied emissions are responsible for 11% of annual greenhouse gas (GHG) emissions globally, an increase in embodied emissions from new construction will put tremendous additional pressure on the natural environment. To investigate the environmental impact of timber and potential of mitigating the increase in embodied GHG emissions from new residential constructions, a life cycle assessment (LCA) is performed for the production stage of three low-energy modular buildings. The results suggested that by substituting reinforced concrete (RC) and masonry (M) with cross-laminated timber (CLT) in the building structure, 14.62% and 12.94% of emissions could be avoided on a building level, respectively. However, the substitution leads to a significant increase in land use impact. In order to get a sense of mitigation potential on the larger scale, the mitigation potential of embodied GHG emissions is investigated for an expected residential building stock new floor area growth predictions depending on the regional residential building structural material choice in the world key regions for periods from 2017 to 2060. Under the assumptions made, the preliminary results suggest that by 2060 a certain amount of emissions could be avoided if conventional structural materials were substituted with CLT, however, emissions from new floor area additions are still substantial. Moreover, global GHG mitigation potential raises new concerns and questions that need to be further investigated. In addition, the importance of considering the land use impact in the LCA studies of bio-based construction materials is highlighted. © 2020 Institute of Physics Publishing. All rights reserved. | S54: Artificial life; Environmental impact; Floors; Gas emissions; Housing; Land use; Life cycle; Modular construction; Reinforced concrete; Sustainable development; Timber; Urban growth; Building structure; Embodied emissions; Life Cycle Assessment (LCA); Modular buildings; Natural environments; Residential building; Residential building stocks; Residential construction; Greenhouse gases | T54: I. Lukić; Faculty of Civil Engineering, Transportation Engineering, and Architecture, University of Maribor, Maribor, Smetanova Ulica 17, 2000, Slovenia; email: iva.lukic1@um.si | U54: Wallbaum H.; Hollberg A.; Thuvander L.; Femenias P.; Kurkowska I.; Mjornell K.; Fudge C. | V54: IOP Publishing Ltd | W54: 17551307 | AA54: English | AB54: IOP Conf. Ser. Earth Environ. Sci. | AC54: Conference paper | AD54: Final | AE54: All Open Access; Gold Open Access | AF54: Scopus | AG54: 2-s2.0-85097174625
A55: Bao Y.; Han Y.; Xu Z.; Lu W.; Yue K.; Lu B. | B55: 57226552124; 59949868700; 57876749200; 55484288800; 53880894800; 57272417300 | C55: Vibration performance of cross-laminated timber (CLT)-concrete composite floors considering the section thickness ratio between CLT panels and concrete slabs | D55: 2025 | E55: Engineering Structures | F55: 340 | H55: 120783 | L55: 3 | M55: 10.1016/j.engstruct.2025.120783 | N55: https://www.scopus.com/pages/publications/105008338824?origin=resultslist | O55: College of Civil Engineering, Nanjing Tech University, Nanjing, 211800, China | P55: Bao Y., College of Civil Engineering, Nanjing Tech University, Nanjing, 211800, China; Han Y., College of Civil Engineering, Nanjing Tech University, Nanjing, 211800, China; Xu Z., College of Civil Engineering, Nanjing Tech University, Nanjing, 211800, China; Lu W., College of Civil Engineering, Nanjing Tech University, Nanjing, 211800, China; Yue K., College of Civil Engineering, Nanjing Tech University, Nanjing, 211800, China; Lu B., College of Civil Engineering, Nanjing Tech University, Nanjing, 211800, China | Q55: Cross-laminated timber (CLT)-concrete composite floor has significant potential for application in multi-storey and long-span modern timber structures due to its excellent mechanical properties. Typically, the design of timber floors is governed by serviceability requirements, such as deflection and vibration, rather than by strength limits. In response, this study presents a series of investigations on the vibration performance of CLT-concrete composite (CCC) floor. Taking component thickness as the design parameter, six CCC floor strips were fabricated and their static and dynamic characteristics were tested. The test results indicated that while the concrete slab significantly enhanced the floor's bending stiffness, its high density led to a reduction in the floor's fundamental frequency. Furthermore, the vibration performance of CCC floor strips was predicted using theoretical calculations and finite element (FE) simulations. The results from both analytical methods were accurate, exhibiting an absolute error of less than 15 %. Finally, parametric numerical analyses were conducted using the two analytical methods to determine the optimal section thickness ratio of the two components in CCC floors. © 2025 | R55: CLT-concrete composite floor; Dynamic tests; Fundamental frequency; Numerical analysis; Vibration performance | S55: Concrete slabs; Concrete testing; Laminated composites; Laminating; Numerical methods; Timber; Vibration analysis; Wooden floors; Composite floors; Concrete composites; Cross laminated; Cross-laminated timber-concrete composite floor; Dynamic tests; Fundamental frequencies; Laminated timber; Performance; Timber-concrete composites; Vibration performance; composite; concrete; design; finite element method; floor; multistorey building; stiffness; theoretical study; timber; vibration; Natural frequencies | T55: W. Lu; College of Civil Engineering, Nanjing Tech University, Nanjing, 211800, China; email: wdlu@njtech.edu.cn | V55: Elsevier Ltd | W55: 1410296 | Y55: ENSTD | AA55: English | AB55: Eng. Struct. | AC55: Article | AD55: Final | AF55: Scopus | AG55: 2-s2.0-105008338824
A56: Spera L.; Sciomenta M.; Bedon C.; Fragiacomo M. | B56: 57220036339; 57201682080; 57217221032; 34770161400 | C56: Out-of-Plane Strengthening of Existing Timber Floors with Cross Laminated Timber Panels Made of Short Supply Chain Beech | D56: 2024 | E56: Buildings | F56: 14 | G56: 3 | H56: 749 | L56: 5 | M56: 10.3390/buildings14030749 | N56: https://www.scopus.com/pages/publications/85190847540?origin=resultslist | O56: Department of Civil, Construction-Architectural and Environmental Engineering, University of L’Aquila, L’Aquila, 67100, Italy; Department of Engineering and Architecture, University of Trieste, Trieste, 34127, Italy | P56: Spera L., Department of Civil, Construction-Architectural and Environmental Engineering, University of L’Aquila, L’Aquila, 67100, Italy; Sciomenta M., Department of Civil, Construction-Architectural and Environmental Engineering, University of L’Aquila, L’Aquila, 67100, Italy; Bedon C., Department of Engineering and Architecture, University of Trieste, Trieste, 34127, Italy; Fragiacomo M., Department of Civil, Construction-Architectural and Environmental Engineering, University of L’Aquila, L’Aquila, 67100, Italy | Q56: Establishing short supply chains for timber has become important especially in Italy, which is an historically wood-importer country. Timber is an environmentally friendly construction material and a potential mean to reduce carbon footprint produced every year by the building sector. In addition to its sustainability benefits, reversible strengthening interventions can be attained for existing structures. As such, timber can be efficiently used to preserve and protect historical buildings which are, due to architectural and aesthetic values, fundamental components of the Italian cultural heritage. In this study, the use and potential of novel cross-laminated (X-Lam or CLT) timber panels made of Italian hardwood (i.e., beech) for strengthening of existing timber floors is investigated. A quantitative comparison between the mechanical performances of the proposed wood-based product and common retrofitting techniques, such as double-crossed timber planks and reinforced concrete slabs, is carried out in terms of bending stiffness (which is evaluated according to Eurocode 5), influence of weight and reversibility of intervention. It is shown that CLT panels represent a good compromise/alternative for the realisation of reversible and sustainable reinforcing interventions, with rather well promising performances. © 2024 by the authors. Licensee MDPI, Basel, Switzerland. | R56: beech (Fagus sylvatica L.); composite sections; Cross Laminated Timber (CLT); out-of-plane stiffness; strengthening interventions; wooden floors | S56: Carbon footprint; Concrete slabs; Floors; Hardwoods; Laminating; Reinforced concrete; Stiffness; Supply chains; Beech (fagi sylvaticum L); Beech (Fagus sylvatica L.); Composite sections; Cross laminated; Cross laminated timber; Laminated timber; Out-of-plane; Out-of-plane stiffness; Strengthening intervention; Timber floors; Timber | T56: C. Bedon; Department of Engineering and Architecture, University of Trieste, Trieste, 34127, Italy; email: chiara.bedon@dia.units.it | V56: Multidisciplinary Digital Publishing Institute (MDPI) | W56: 20755309 | AA56: English | AB56: Buildings | AC56: Article | AD56: Final | AE56: All Open Access; Gold Open Access; Green Open Access | AF56: Scopus | AG56: 2-s2.0-85190847540
A57: Ajmal M.; Ahmed D.; Asiz A. | B57: 57188748405; 57217208973; 6506926796 | C57: Structural performance of hybrid tall buildings designed using ultra-lightweight floor slabs | D57: 2016 | E57: Insights and Innovations in Structural Engineering, Mechanics and Computation - Proceedings of the 6th International Conference on Structural Engineering, Mechanics and Computation, SEMC 2016 | I57: 983 | J57: 987 | K57: =scopus[[#This Row],[Page end]]-scopus[[#This Row],[Page start]] -> 4 | L57: 5 | M57: 10.1201/9781315641645-162 | N57: https://www.scopus.com/pages/publications/85013092875?origin=resultslist | O57: Department of Civil Engineering, King Fahd University of Petroleum and Minerals, Dhahran, Saudi Arabia; Department of Civil Engineering, Prince Mohammad Bin Fahd University, Dhahran, Saudi Arabia | P57: Ajmal M., Department of Civil Engineering, King Fahd University of Petroleum and Minerals, Dhahran, Saudi Arabia; Ahmed D., Department of Civil Engineering, Prince Mohammad Bin Fahd University, Dhahran, Saudi Arabia; Asiz A., Department of Civil Engineering, Prince Mohammad Bin Fahd University, Dhahran, Saudi Arabia | Q57: The main objective of this study is to investigate feasibility of using Ultra-Lightweight (ULW) slab in floor system of tall building in combination with rigid steel frame and Reinforced Concrete (RC) shear wall as the lateral load resisting systems. The main vehicle is numerical case studies of forty story buildings in which their floor systems constructed using conventional (RC slab) only, non-conventional (ULW slab) only, and hybrid between these two slabs. In the hybrid floor cases, combinations of lower story RC slabs and upper story ULW slabs will be conducted. For example, the first twenty five floor levels will be designed using traditional composite action between RC and steel floor framing, while the upper fifteen story floor levels will be designed using ULW slab in composite action with steel floor framing. In addition to dead and live loads, major lateral load considered will be extreme wind and earthquake loads suited for middle-east region. The outcome will be comparison of structural performance amongst these floor systems including: total drift, inter-story drift, inter-story shears, base reactions, and structural dynamic performances. Also steel demand on the main steel skeleton will be compared to each other. The ULW slab could be made of lightweight materials having high vertical and lateral stiffness. In this study however, the ULW floor slab will be made of high strength Cross Laminated Timber (CLT). Within last two decades, CLT slabs have been used widely in Europe for low-rise building applications. In combination with steel and/or reinforced concrete frames, CLT has potential application to be used in a very demanding tall building industry in the middle-east areas due to its strength, lightness, low demand on foundation, architecturally appealing, and green or environmentally friendly. The outcome of this study is intended to give structural engineers and architects alternative in designing floor systems of tall buildings. © 2016 Taylor & Francis Group, London. | R57: Cross laminated timber; Hybrid floor; Reinforced concrete shear wall; Steel frame; Structural performance; Ultra-lightweight slab | S57: Construction industry; Laminating; Mechanics; Reinforced concrete; Shear walls; Steel construction; Structural analysis; Structural dynamics; Structural frames; Tall buildings; Timber; Cross laminated; Reinforced concrete shear walls; Steel frame; Structural performance; Ultra lightweights; Floors | U57: Zingoni A. | V57: CRC Press/Balkema | X57: 978-113802927-9 | AA57: English | AB57: Insights Innov. Struct. Eng. Mech. Comput. Proc. Int. Conf. Struct. Eng. Mech. Comput. | AC57: Conference paper | AD57: Final | AF57: Scopus | AG57: 2-s2.0-85013092875
A58: Shin B.; Chang S.J.; Wi S.; Kim S. | B58: 57695174600; 55982427600; 56730295700; 8542733000 | C58: Estimation of energy demand and greenhouse gas emission reduction effect of cross-laminated timber (CLT) hybrid wall using life cycle assessment for urban residential planning | D58: 2023 | E58: Renewable and Sustainable Energy Reviews | F58: 185 | H58: 113604 | L58: 38 | M58: 10.1016/j.rser.2023.113604 | N58: https://www.scopus.com/pages/publications/85166924663?origin=resultslist | O58: Department of Architecture and Architectural Engineering, Yonsei University, Seoul, 03722, South Korea; Department of Interior Materials Engineering, College of Construction and Environmental Engineering, Gyeongsang National University, Jinju, 52725, South Korea; School of Architecture, Seoul National University of Science and Technology, Seoul, 01811, South Korea | P58: Shin B., Department of Architecture and Architectural Engineering, Yonsei University, Seoul, 03722, South Korea; Chang S.J., Department of Interior Materials Engineering, College of Construction and Environmental Engineering, Gyeongsang National University, Jinju, 52725, South Korea; Wi S., School of Architecture, Seoul National University of Science and Technology, Seoul, 01811, South Korea; Kim S., Department of Architecture and Architectural Engineering, Yonsei University, Seoul, 03722, South Korea | Q58: The building and construction sector accounted for 36% of final energy use and 37% of energy and process-related carbon dioxide (CO2) emissions in 2020. According to a recent study, if the global population grows to 9.3 billion by 2050, new infrastructure development will cause approximately 350 Gt of CO2 emissions, corresponding to 35–60% of the remaining carbon budget available up to 2050 if the average temperature increase is to be limited to 2 °C. Material substitution is one way to reduce embodied energy and CO2 emissions. Cross-laminated timber (CLT), a bio-based material, can be an alternative to concrete and steel, which are the most energy- and carbon-intensive materials. However, there is a limit to the immediate application of CLT to the entire building. This study confirmed greenhouse gas (GHG) emission and energy consumption reductions when CLT was applied to the exterior walls of 52 apartment building types. Substituting CLT for concrete in the exterior walls resulted in a 44.6% savings in GHG emissions and 49.3% in energy demand. GHG emissions per floor were reduced by −16,906 kg CO2-eq, while energy consumption per floor was reduced by −256,896 MJ. If CLT is used in 30% of the exterior walls of the 800,000 houses planned to be constructed in Seoul by 2030, the energy savings and GHG reduction effect are expected to be −11,495 TJ and −0.86 Mt CO2-eq, respectively. © 2023 Elsevier Ltd | R58: Cross-laminated timber (CLT); Embodied carbon; Embodied energy; Life cycle assessment; Material substitution; Regression analysis | S58: Budget control; Concretes; Construction industry; Emission control; Energy conservation; Energy management; Energy utilization; Floors; Gas emissions; Greenhouse effect; Greenhouse gases; Laminating; Life cycle; Regression analysis; Timber; Walls (structural partitions); Cross laminated; Cross-laminated timber; Embodied carbons; Embodied energy; Energy demands; Exterior walls; Greenhouse gas emissions; Laminated timber; Life cycle assessment; Materials substitutions; Carbon dioxide | T58: S. Kim; Department of Architecture and Architectural Engineering, Yonsei University, Seoul, 03722, South Korea; email: kimsumin@yonsei.ac.kr | V58: Elsevier Ltd | W58: 13640321 | Y58: RSERF | AA58: English | AB58: Renewable Sustainable Energy Rev | AC58: Article | AD58: Final | AF58: Scopus | AG58: 2-s2.0-85166924663
A59: Mirdad M.A.H.; Chui Y.H. | B59: 57190062072; 7004982369 | C59: Behaviour of mass timber panel-concrete connections with inclined self-tapping screws and insulation layer | D59: 2018 | E59: WCTE 2018 - World Conference on Timber Engineering | L59: 4 | N59: https://www.scopus.com/pages/publications/85058182839?origin=resultslist | O59: University of Alberta, Canada | P59: Mirdad M.A.H., University of Alberta, Canada; Chui Y.H., University of Alberta, Canada | Q59: The Mass Timber Panel-Concrete (MTPC) composite floor system considered in this paper consists of a Mass Timber Panel (MTP) connected to reinforced concrete slab with Self-Tapping Screw (STS) connector and a sound insulation layer in between. This type of composite floor system is intended for mid-to high-rise building applications. Two types of MTPs with normal weight concrete, two insulation thicknesses, two screw embedment lengths and two screw angles were investigated through connection tests to characterize connection stiffness and strength. The main goal of this connection test program was to provide preliminary test data to assist in the development of a model to predict connections lateral stiffness and strength under consideration of insulation thickness, screw angle, withdrawal and embedment properties of screws in MTP. Connection test results show that screws at an insertion angle of 30° have a higher stiffness and strength along with a larger embedment length compared to the screws at a 45° angle and smaller embedment length. Stiffness seemed to be more susceptible to the influence of presence of insulation compared to strength with 40-65% reduction of stiffness and 10-20% reduction of strength were noticed for an insulation thickness of 5 mm. Screws in CLT showed higher strength while screws in CLP showed higher stiffness but the difference is insignificant. © WCTE 2018 Committee. | R59: Composite floor systems; Insulation layer; Mass timber panel; Self-tapping screw | S59: Concrete slabs; Floors; Reinforced concrete; Screws; Software testing; Stiffness; Tall buildings; Timber; Composite floor systems; Connection stiffness; High rise building; Insulation layers; Insulation thickness; Mass timber panel; Normal weight concrete; Self-tapping screws; Sound insulation | V59: World Conference on Timber Engineering (WCTE) | AA59: English | AB59: WCTE - World Conf. Timber Engi. | AC59: Conference paper | AD59: Final | AF59: Scopus | AG59: 2-s2.0-85058182839
A60: Paraire E.; Appel S. | B60: 57223800152; 26532440200 | C60: STRUCTURAL DYNAMIC CALCULATIONS OF TRAFFIC INDUCED VIBRATIONS IN MODERN CROSS LAMINATED TIMBER CONSTRUCTIONS | D60: 2024 | E60: Proceedings of the International Congress on Sound and Vibration | L60: 0 | N60: https://www.scopus.com/pages/publications/85205345901?origin=resultslist | O60: GuD Geotechnik und Dynamik Consult GmbH, Berlin, Germany | P60: Paraire E., GuD Geotechnik und Dynamik Consult GmbH, Berlin, Germany; Appel S., GuD Geotechnik und Dynamik Consult GmbH, Berlin, Germany | Q60: Timber buildings are becoming increasingly popular due to their sustainability and ease of construction. The development of modern construction methods with cross-laminated timber (CLT) now allows for the erection of high-rise timber buildings. The increase of timber building projects in cities with dense traffic networks means that constructions often take place in locations with a high potential for vibration problems. The forecast of traffic induced vibrations using finite element (FE) simulations is a well-proven design method for reinforced concrete structures. However, the structural dynamic behaviour of multi-storey timber buildings is still largely unexplored. While various research projects are attempting to address this topic, practical and reliable solutions are currently needed for the design of ongoing construction projects. The floor vibration response to road and rail traffic has been investigated for CLT building projects using FE models. The computational approaches and the modelling of the CLT structure are based on measurements and results from a research group. The models include both timber and hybrid timber-concrete floor constructions, as well as their coupling with floating screeds. © 2024 Proceedings of the International Congress on Sound and Vibration. All rights reserved. | R60: finite element methods; timber constructions; traffic vibrations | S60: Architectural acoustics; Concrete buildings; Structural dynamics; Tall buildings; Vibration analysis; Wooden floors; Building projects; Construction method; Cross laminated; Dynamics calculations; Element method; Laminated timber; Timber buildings; Timber construction; Traffic induced vibrations; Traffic vibrations; Wooden buildings | U60: van Keulen W.; Kok J. | V60: Society of Acoustics | W60: 23293675 | X60: 978-909039058-1 | AA60: English | AB60: Proc. Int. Congr. Sound Vib. | AC60: Conference paper | AD60: Final | AF60: Scopus | AG60: 2-s2.0-85205345901
A61: Ussher E.; Smith I. | B61: 56557007300; 7404426235 | C61: Predicting vibration behaviour of cross laminated timber floors | D61: 2015 | E61: IABSE Conference, Nara 2015: Elegance in Structures - Report | I61: 252 | J61: 253 | K61: =scopus[[#This Row],[Page end]]-scopus[[#This Row],[Page start]] -> 1 | L61: 5 | N61: https://www.scopus.com/pages/publications/84971231488?origin=resultslist | O61: Univ. New Brunswick, Fredericton, Canada | P61: Ussher E., Univ. New Brunswick, Fredericton, Canada; Smith I., Univ. New Brunswick, Fredericton, Canada | Q61: Ultra-lightweight products like Cross-Laminated-Timber (CLT) have entered the marketplace as alternatives to cast in-sitn or precast reinforced concrete (RC) for construction of floor slabs. The primary advantage of using lightweight materials is that they reduce structural demands on supporting elements. However, lightweight slabs tend to exhibit higher levels of acceleration than RC slabs when subjected to dynamic loads, making it prudent to pay close attention to vibration serviceability when designing CLT slabs. Discussion here addresses a detailed finite element (FE) analysis approach as the reference point for defining accuracy capabilities of simple dynamic analysis formulas. It is concluded CLT floor slabs embody complexities in their modal responses that are beyond abilities of simple engineering formulas to predict. | R61: Cross-laminated-timber; Design; Finite element analysis; Modal frequencies; Mode shapes; Peak acceleration; Vibration serviceability | S61: Concrete products; Design; Dynamic loads; Finite element method; Floors; Laminating; Reinforced concrete; Structural panels; Timber; Cross laminated; Modal frequency; Mode shapes; Peak acceleration; Vibration serviceability; Vibration analysis | V61: International Association for Bridge and Structural Engineering (IABSE) | X61: 978-385748138-3 | AA61: English | AB61: IABSE Conf., Nara: Elegance Struct. - Rep. | AC61: Conference paper | AD61: Final | AF61: Scopus | AG61: 2-s2.0-84971231488
